[{"className":"Part","name":"12277","parentId":"00042e25-5c6f-3ac7-7e1f-00004cddd851","path":"ServerStorage.Maps.Desert.voxels.12277","properties":{"Anchored":{"type":"bool","value":true},"AudioCanCollide":{"type":"bool","value":true},"BackSurface":{"type":"Enum","value":{"enumType":"SurfaceType","value":"Smooth"}},"BottomSurface":{"type":"Enum","value":{"enumType":"SurfaceType","value":"SmoothNoOutlines"}},"CFrame":{"type":"CFrame","value":{"position":[49,1,26],"rotation":[1,0,0,0,1,0,0,0,1]}},"CanCollide":{"type":"bool","value":true},"CanQuery":{"type":"bool","value":true},"CanTouch":{"type":"bool","value":true},"Capabilities":{"type":"Enum","value":{"enumType":"SecurityCapabilities","value":""}},"CastShadow":{"type":"bool","value":true},"CollisionGroup":{"type":"string","value":"Default"},"CollisionGroupId":{"type":"int","value":0},"CustomPhysicalProperties":{"type":"nil"},"EnableFluidForces":{"type":"bool","value":true},"FrontSurface":{"type":"Enum","value":{"enumType":"SurfaceType","value":"Smooth"}},"LeftSurface":{"type":"Enum","value":{"enumType":"SurfaceType","value":"Smooth"}},"Locked":{"type":"bool","value":false},"Massless":{"type":"bool","value":false},"Material":{"type":"Enum","value":{"enumType":"Material","value":"Concrete"}},"PivotOffset":{"type":"CFrame","value":{"position":[0,0,0],"rotation":[1,0,0,0,1,0,0,0,1]}},"Reflectance":{"type":"float","value":0},"RightSurface":{"type":"Enum","value":{"enumType":"SurfaceType","value":"Smooth"}},"RootPriority":{"type":"int","value":0},"TopSurface":{"type":"Enum","value":{"enumType":"SurfaceType","value":"SmoothNoOutlines"}},"Transparency":{"type":"float","value":0}},"referenceId":"00048410-f20e-c59e-5aaf-00000e773dd9"},{"className":"Weld","name":"Weld","parentId":"00048410-f20e-c59e-5aaf-00000e773dd9","path":"ServerStorage.Maps.Desert.voxels.12277.Weld","properties":{"C0":{"type":"CFrame","value":{"position":[0,-0.5,0],"rotation":[1,0,0,0,0,-1,0,1,0]}},"C1":{"type":"CFrame","value":{"position":[-75.5,0.5,-98.5],"rotation":[1,0,0,0,0,-1,0,1,0]}},"Capabilities":{"type":"Enum","value":{"enumType":"SecurityCapabilities","value":""}},"Enabled":{"type":"bool","value":true},"Part0":{"type":"Enum","value":{"enumType":"BasePart","value":"12277"}},"Part1":{"type":"Enum","value":{"enumType":"BasePart","value":"PlayerSpawn"}}},"referenceId":"00048411-096e-1abd-3296-00004f196299"},{"className":"Part","name":"12278","parentId":"00042e25-5c6f-3ac7-7e1f-00004cddd851","path":"ServerStorage.Maps.Desert.voxels.12278","properties":{"Anchored":{"type":"bool","value":true},"AudioCanCollide":{"type":"bool","value":true},"BackSurface":{"type":"Enum","value":{"enumType":"SurfaceType","value":"Smooth"}},"BottomSurface":{"type":"Enum","value":{"enumType":"SurfaceType","value":"SmoothNoOutlines"}},"CFrame":{"type":"CFrame","value":{"position":[49,1,27],"rotation":[1,0,0,0,1,0,0,0,1]}},"CanCollide":{"type":"bool","value":true},"CanQuery":{"type":"bool","value":true},"CanTouch":{"type":"bool","value":true},"Capabilities":{"type":"Enum","value":{"enumType":"SecurityCapabilities","value":""}},"CastShadow":{"type":"bool","value":true},"CollisionGroup":{"type":"string","value":"Default"},"CollisionGroupId":{"type":"int","value":0},"CustomPhysicalProperties":{"type":"nil"},"EnableFluidForces":{"type":"bool","value":true},"FrontSurface":{"type":"Enum","value":{"enumType":"SurfaceType","value":"Smooth"}},"LeftSurface":{"type":"Enum","value":{"enumType":"SurfaceType","value":"Smooth"}},"Locked":{"type":"bool","value":false},"Massless":{"type":"bool","value":false},"Material":{"type":"Enum","value":{"enumType":"Material","value":"Concrete"}},"PivotOffset":{"type":"CFrame","value":{"position":[0,0,0],"rotation":[1,0,0,0,1,0,0,0,1]}},"Reflectance":{"type":"float","value":0},"RightSurface":{"type":"Enum","value":{"enumType":"SurfaceType","value":"Smooth"}},"RootPriority":{"type":"int","value":0},"TopSurface":{"type":"Enum","value":{"enumType":"SurfaceType","value":"SmoothNoOutlines"}},"Transparency":{"type":"float","value":0}},"referenceId":"00048412-2971-ebb6-e562-000025143463"},{"className":"Weld","name":"Weld","parentId":"00048412-2971-ebb6-e562-000025143463","path":"ServerStorage.Maps.Desert.voxels.12278.Weld","properties":{"C0":{"type":"CFrame","value":{"position":[0,-0.5,0],"rotation":[1,0,0,0,0,-1,0,1,0]}},"C1":{"type":"CFrame","value":{"position":[-75.5,0.5,-97.5],"rotation":[1,0,0,0,0,-1,0,1,0]}},"Capabilities":{"type":"Enum","value":{"enumType":"SecurityCapabilities","value":""}},"Enabled":{"type":"bool","value":true},"Part0":{"type":"Enum","value":{"enumType":"BasePart","value":"12278"}},"Part1":{"type":"Enum","value":{"enumType":"BasePart","value":"PlayerSpawn"}}},"referenceId":"00048413-51d2-84ba-04c7-000041014425"},{"className":"Part","name":"12458","parentId":"00042e25-5c6f-3ac7-7e1f-00004cddd851","path":"ServerStorage.Maps.Desert.voxels.12458","properties":{"Anchored":{"type":"bool","value":true},"AudioCanCollide":{"type":"bool","value":true},"BackSurface":{"type":"Enum","value":{"enumType":"SurfaceType","value":"Smooth"}},"BottomSurface":{"type":"Enum","value":{"enumType":"SurfaceType","value":"SmoothNoOutlines"}},"CFrame":{"type":"CFrame","value":{"position":[49,0.5,207],"rotation":[1,0,0,0,1,0,0,0,1]}},"CanCollide":{"type":"bool","value":true},"CanQuery":{"type":"bool","value":true},"CanTouch":{"type":"bool","value":true},"Capabilities":{"type":"Enum","value":{"enumType":"SecurityCapabilities","value":""}},"CastShadow":{"type":"bool","value":false},"CollisionGroup":{"type":"string","value":"Default"},"CollisionGroupId":{"type":"int","value":0},"CustomPhysicalProperties":{"type":"nil"},"EnableFluidForces":{"type":"bool","value":true},"FrontSurface":{"type":"Enum","value":{"enumType":"SurfaceType","value":"Smooth"}},"LeftSurface":{"type":"Enum","value":{"enumType":"SurfaceType","value":"Smooth"}},"Locked":{"type":"bool","value":false},"Massless":{"type":"bool","value":false},"Material":{"type":"Enum","value":{"enumType":"Material","value":"Plastic"}},"PivotOffset":{"type":"CFrame","value":{"position":[0,0,0],"rotation":[1,0,0,0,1,0,0,0,1]}},"Reflectance":{"type":"float","value":0},"RightSurface":{"type":"Enum","value":{"enumType":"SurfaceType","value":"Smooth"}},"RootPriority":{"type":"int","value":0},"TopSurface":{"type":"Enum","value":{"enumType":"SurfaceType","value":"SmoothNoOutlines"}},"Transparency":{"type":"float","value":0}},"referenceId":"00048414-89be-bd1c-4c0d-00004b03e587"},{"className":"Part","name":"12395","parentId":"00042e25-5c6f-3ac7-7e1f-00004cddd851","path":"ServerStorage.Maps.Desert.voxels.12395","properties":{"Anchored":{"type":"bool","value":true},"AudioCanCollide":{"type":"bool","value":true},"BackSurface":{"type":"Enum","value":{"enumType":"SurfaceType","value":"Smooth"}},"BottomSurface":{"type":"Enum","value":{"enumType":"SurfaceType","value":"SmoothNoOutlines"}},"CFrame":{"type":"CFrame","value":{"position":[49,1,144],"rotation":[1,0,0,0,1,0,0,0,1]}},"CanCollide":{"type":"bool","value":true},"CanQuery":{"type":"bool","value":true},"CanTouch":{"type":"bool","value":true},"Capabilities":{"type":"Enum","value":{"enumType":"SecurityCapabilities","value":""}},"CastShadow":{"type":"bool","value":true},"CollisionGroup":{"type":"string","value":"Default"},"CollisionGroupId":{"type":"int","value":0},"CustomPhysicalProperties":{"type":"nil"},"EnableFluidForces":{"type":"bool","value":true},"FrontSurface":{"type":"Enum","value":{"enumType":"SurfaceType","value":"Smooth"}},"LeftSurface":{"type":"Enum","value":{"enumType":"SurfaceType","value":"Smooth"}},"Locked":{"type":"bool","value":false},"Massless":{"type":"bool","value":false},"Material":{"type":"Enum","value":{"enumType":"Material","value":"Concrete"}},"PivotOffset":{"type":"CFrame","value":{"position":[0,0,0],"rotation":[1,0,0,0,1,0,0,0,1]}},"Reflectance":{"type":"float","value":0},"RightSurface":{"type":"Enum","value":{"enumType":"SurfaceType","value":"Smooth"}},"RootPriority":{"type":"int","value":0},"TopSurface":{"type":"Enum","value":{"enumType":"SurfaceType","value":"SmoothNoOutlines"}},"Transparency":{"type":"float","value":0}},"referenceId":"00048415-d57b-8cf2-7936-000038e0f30b"},{"className":"Weld","name":"Weld","parentId":"00048415-d57b-8cf2-7936-000038e0f30b","path":"ServerStorage.Maps.Desert.voxels.12395.Weld","properties":{"C0":{"type":"CFrame","value":{"position":[0,-0.5,0],"rotation":[1,0,0,0,0,-1,0,1,0]}},"C1":{"type":"CFrame","value":{"position":[-75.5,0.5,19.5],"rotation":[1,0,0,0,0,-1,0,1,0]}},"Capabilities":{"type":"Enum","value":{"enumType":"SecurityCapabilities","value":""}},"Enabled":{"type":"bool","value":true},"Part0":{"type":"Enum","value":{"enumType":"BasePart","value":"12395"}},"Part1":{"type":"Enum","value":{"enumType":"BasePart","value":"PlayerSpawn"}}},"referenceId":"00048416-7151-5dc0-735d-00006ac027b5"},{"className":"Part","name":"12302","parentId":"00042e25-5c6f-3ac7-7e1f-00004cddd851","path":"ServerStorage.Maps.Desert.voxels.12302","properties":{"Anchored":{"type":"bool","value":true},"AudioCanCollide":{"type":"bool","value":true},"BackSurface":{"type":"Enum","value":{"enumType":"SurfaceType","value":"Smooth"}},"BottomSurface":{"type":"Enum","value":{"enumType":"SurfaceType","value":"SmoothNoOutlines"}},"CFrame":{"type":"CFrame","value":{"position":[49,1,51],"rotation":[1,0,0,0,1,0,0,0,1]}},"CanCollide":{"type":"bool","value":true},"CanQuery":{"type":"bool","value":true},"CanTouch":{"type":"bool","value":true},"Capabilities":{"type":"Enum","value":{"enumType":"SecurityCapabilities","value":""}},"CastShadow":{"type":"bool","value":true},"CollisionGroup":{"type":"string","value":"Default"},"CollisionGroupId":{"type":"int","value":0},"CustomPhysicalProperties":{"type":"nil"},"EnableFluidForces":{"type":"bool","value":true},"FrontSurface":{"type":"Enum","value":{"enumType":"SurfaceType","value":"Smooth"}},"LeftSurface":{"type":"Enum","value":{"enumType":"SurfaceType","value":"Smooth"}},"Locked":{"type":"bool","value":false},"Massless":{"type":"bool","value":false},"Material":{"type":"Enum","value":{"enumType":"Material","value":"Concrete"}},"PivotOffset":{"type":"CFrame","value":{"position":[0,0,0],"rotation":[1,0,0,0,1,0,0,0,1]}},"Reflectance":{"type":"float","value":0},"RightSurface":{"type":"Enum","value":{"enumType":"SurfaceType","value":"Smooth"}},"RootPriority":{"type":"int","value":0},"TopSurface":{"type":"Enum","value":{"enumType":"SurfaceType","value":"SmoothNoOutlines"}},"Transparency":{"type":"float","value":0}},"referenceId":"00048417-0d5b-aabf-c7c3-000071e16dc4"},{"className":"Weld","name":"Weld","parentId":"00048417-0d5b-aabf-c7c3-000071e16dc4","path":"ServerStorage.Maps.Desert.voxels.12302.Weld","properties":{"C0":{"type":"CFrame","value":{"position":[0,-0.5,0],"rotation":[1,0,0,0,0,-1,0,1,0]}},"C1":{"type":"CFrame","value":{"position":[-75.5,0.5,-73.5],"rotation":[1,0,0,0,0,-1,0,1,0]}},"Capabilities":{"type":"Enum","value":{"enumType":"SecurityCapabilities","value":""}},"Enabled":{"type":"bool","value":true},"Part0":{"type":"Enum","value":{"enumType":"BasePart","value":"12302"}},"Part1":{"type":"Enum","value":{"enumType":"BasePart","value":"PlayerSpawn"}}},"referenceId":"00048418-a9a0-e117-e539-0000485edaf3"},{"className":"Part","name":"12333","parentId":"00042e25-5c6f-3ac7-7e1f-00004cddd851","path":"ServerStorage.Maps.Desert.voxels.12333","properties":{"Anchored":{"type":"bool","value":true},"AudioCanCollide":{"type":"bool","value":true},"BackSurface":{"type":"Enum","value":{"enumType":"SurfaceType","value":"Smooth"}},"BottomSurface":{"type":"Enum","value":{"enumType":"SurfaceType","value":"SmoothNoOutlines"}},"CFrame":{"type":"CFrame","value":{"position":[49,1,82],"rotation":[1,0,0,0,1,0,0,0,1]}},"CanCollide":{"type":"bool","value":true},"CanQuery":{"type":"bool","value":true},"CanTouch":{"type":"bool","value":true},"Capabilities":{"type":"Enum","value":{"enumType":"SecurityCapabilities","value":""}},"CastShadow":{"type":"bool","value":true},"CollisionGroup":{"type":"string","value":"Default"},"CollisionGroupId":{"type":"int","value":0},"CustomPhysicalProperties":{"type":"nil"},"EnableFluidForces":{"type":"bool","value":true},"FrontSurface":{"type":"Enum","value":{"enumType":"SurfaceType","value":"Smooth"}},"LeftSurface":{"type":"Enum","value":{"enumType":"SurfaceType","value":"Smooth"}},"Locked":{"type":"bool","value":false},"Massless":{"type":"bool","value":false},"Material":{"type":"Enum","value":{"enumType":"Material","value":"Concrete"}},"PivotOffset":{"type":"CFrame","value":{"position":[0,0,0],"rotation":[1,0,0,0,1,0,0,0,1]}},"Reflectance":{"type":"float","value":0},"RightSurface":{"type":"Enum","value":{"enumType":"SurfaceType","value":"Smooth"}},"RootPriority":{"type":"int","value":0},"TopSurface":{"type":"Enum","value":{"enumType":"SurfaceType","value":"SmoothNoOutlines"}},"Transparency":{"type":"float","value":0}},"referenceId":"00048419-f961-4f1e-e88b-000044a47d0e"},{"className":"Weld","name":"Weld","parentId":"00048419-f961-4f1e-e88b-000044a47d0e","path":"ServerStorage.Maps.Desert.voxels.12333.Weld","properties":{"C0":{"type":"CFrame","value":{"position":[0,-0.5,0],"rotation":[1,0,0,0,0,-1,0,1,0]}},"C1":{"type":"CFrame","value":{"position":[-75.5,0.5,-42.5],"rotation":[1,0,0,0,0,-1,0,1,0]}},"Capabilities":{"type":"Enum","value":{"enumType":"SecurityCapabilities","value":""}},"Enabled":{"type":"bool","value":true},"Part0":{"type":"Enum","value":{"enumType":"BasePart","value":"12333"}},"Part1":{"type":"Enum","value":{"enumType":"BasePart","value":"PlayerSpawn"}}},"referenceId":"0004841a-a06e-5bb4-1dbd-000049b4a831"},{"className":"Part","name":"12377","parentId":"00042e25-5c6f-3ac7-7e1f-00004cddd851","path":"ServerStorage.Maps.Desert.voxels.12377","properties":{"Anchored":{"type":"bool","value":true},"AudioCanCollide":{"type":"bool","value":true},"BackSurface":{"type":"Enum","value":{"enumType":"SurfaceType","value":"Smooth"}},"BottomSurface":{"type":"Enum","value":{"enumType":"SurfaceType","value":"SmoothNoOutlines"}},"CFrame":{"type":"CFrame","value":{"position":[49,1,126],"rotation":[1,0,0,0,1,0,0,0,1]}},"CanCollide":{"type":"bool","value":true},"CanQuery":{"type":"bool","value":true},"CanTouch":{"type":"bool","value":true},"Capabilities":{"type":"Enum","value":{"enumType":"SecurityCapabilities","value":""}},"CastShadow":{"type":"bool","value":true},"CollisionGroup":{"type":"string","value":"Default"},"CollisionGroupId":{"type":"int","value":0},"CustomPhysicalProperties":{"type":"nil"},"EnableFluidForces":{"type":"bool","value":true},"FrontSurface":{"type":"Enum","value":{"enumType":"SurfaceType","value":"Smooth"}},"LeftSurface":{"type":"Enum","value":{"enumType":"SurfaceType","value":"Smooth"}},"Locked":{"type":"bool","value":false},"Massless":{"type":"bool","value":false},"Material":{"type":"Enum","value":{"enumType":"Material","value":"Concrete"}},"PivotOffset":{"type":"CFrame","value":{"position":[0,0,0],"rotation":[1,0,0,0,1,0,0,0,1]}},"Reflectance":{"type":"float","value":0},"RightSurface":{"type":"Enum","value":{"enumType":"SurfaceType","value":"Smooth"}},"RootPriority":{"type":"int","value":0},"TopSurface":{"type":"Enum","value":{"enumType":"SurfaceType","value":"SmoothNoOutlines"}},"Transparency":{"type":"float","value":0}},"referenceId":"0004841b-28f2-06fe-2817-0000405b471d"},{"className":"Weld","name":"Weld","parentId":"0004841b-28f2-06fe-2817-0000405b471d","path":"ServerStorage.Maps.Desert.voxels.12377.Weld","properties":{"C0":{"type":"CFrame","value":{"position":[0,-0.5,0],"rotation":[1,0,0,0,0,-1,0,1,0]}},"C1":{"type":"CFrame","value":{"position":[-75.5,0.5,1.5],"rotation":[1,0,0,0,0,-1,0,1,0]}},"Capabilities":{"type":"Enum","value":{"enumType":"SecurityCapabilities","value":""}},"Enabled":{"type":"bool","value":true},"Part0":{"type":"Enum","value":{"enumType":"BasePart","value":"12377"}},"Part1":{"type":"Enum","value":{"enumType":"BasePart","value":"PlayerSpawn"}}},"referenceId":"0004841c-f48e-da6c-bff6-000079aab981"},{"className":"Part","name":"12442","parentId":"00042e25-5c6f-3ac7-7e1f-00004cddd851","path":"ServerStorage.Maps.Desert.voxels.12442","properties":{"Anchored":{"type":"bool","value":true},"AudioCanCollide":{"type":"bool","value":true},"BackSurface":{"type":"Enum","value":{"enumType":"SurfaceType","value":"Smooth"}},"BottomSurface":{"type":"Enum","value":{"enumType":"SurfaceType","value":"SmoothNoOutlines"}},"CFrame":{"type":"CFrame","value":{"position":[49,1,191],"rotation":[1,0,0,0,1,0,0,0,1]}},"CanCollide":{"type":"bool","value":true},"CanQuery":{"type":"bool","value":true},"CanTouch":{"type":"bool","value":true},"Capabilities":{"type":"Enum","value":{"enumType":"SecurityCapabilities","value":""}},"CastShadow":{"type":"bool","value":true},"CollisionGroup":{"type":"string","value":"Default"},"CollisionGroupId":{"type":"int","value":0},"CustomPhysicalProperties":{"type":"nil"},"EnableFluidForces":{"type":"bool","value":true},"FrontSurface":{"type":"Enum","value":{"enumType":"SurfaceType","value":"Smooth"}},"LeftSurface":{"type":"Enum","value":{"enumType":"SurfaceType","value":"Smooth"}},"Locked":{"type":"bool","value":false},"Massless":{"type":"bool","value":false},"Material":{"type":"Enum","value":{"enumType":"Material","value":"Concrete"}},"PivotOffset":{"type":"CFrame","value":{"position":[0,0,0],"rotation":[1,0,0,0,1,0,0,0,1]}},"Reflectance":{"type":"float","value":0},"RightSurface":{"type":"Enum","value":{"enumType":"SurfaceType","value":"Smooth"}},"RootPriority":{"type":"int","value":0},"TopSurface":{"type":"Enum","value":{"enumType":"SurfaceType","value":"SmoothNoOutlines"}},"Transparency":{"type":"float","value":0}},"referenceId":"0004841d-ae57-e9b6-5fee-0000663ab995"},{"className":"Weld","name":"Weld","parentId":"0004841d-ae57-e9b6-5fee-0000663ab995","path":"ServerStorage.Maps.Desert.voxels.12442.Weld","properties":{"C0":{"type":"CFrame","value":{"position":[0,-0.5,0],"rotation":[1,0,0,0,0,-1,0,1,0]}},"C1":{"type":"CFrame","value":{"position":[-75.5,0.5,66.5],"rotation":[1,0,0,0,0,-1,0,1,0]}},"Capabilities":{"type":"Enum","value":{"enumType":"SecurityCapabilities","value":""}},"Enabled":{"type":"bool","value":true},"Part0":{"type":"Enum","value":{"enumType":"BasePart","value":"12442"}},"Part1":{"type":"Enum","value":{"enumType":"BasePart","value":"PlayerSpawn"}}},"referenceId":"0004841e-5862-c374-03e2-00004562ec3c"},{"className":"Part","name":"12347","parentId":"00042e25-5c6f-3ac7-7e1f-00004cddd851","path":"ServerStorage.Maps.Desert.voxels.12347","properties":{"Anchored":{"type":"bool","value":true},"AudioCanCollide":{"type":"bool","value":true},"BackSurface":{"type":"Enum","value":{"enumType":"SurfaceType","value":"Smooth"}},"BottomSurface":{"type":"Enum","value":{"enumType":"SurfaceType","value":"SmoothNoOutlines"}},"CFrame":{"type":"CFrame","value":{"position":[49,1,96],"rotation":[1,0,0,0,1,0,0,0,1]}},"CanCollide":{"type":"bool","value":true},"CanQuery":{"type":"bool","value":true},"CanTouch":{"type":"bool","value":true},"Capabilities":{"type":"Enum","value":{"enumType":"SecurityCapabilities","value":""}},"CastShadow":{"type":"bool","value":true},"CollisionGroup":{"type":"string","value":"Default"},"CollisionGroupId":{"type":"int","value":0},"CustomPhysicalProperties":{"type":"nil"},"EnableFluidForces":{"type":"bool","value":true},"FrontSurface":{"type":"Enum","value":{"enumType":"SurfaceType","value":"Smooth"}},"LeftSurface":{"type":"Enum","value":{"enumType":"SurfaceType","value":"Smooth"}},"Locked":{"type":"bool","value":false},"Massless":{"type":"bool","value":false},"Material":{"type":"Enum","value":{"enumType":"Material","value":"Concrete"}},"PivotOffset":{"type":"CFrame","value":{"position":[0,0,0],"rotation":[1,0,0,0,1,0,0,0,1]}},"Reflectance":{"type":"float","value":0},"RightSurface":{"type":"Enum","value":{"enumType":"SurfaceType","value":"Smooth"}},"RootPriority":{"type":"int","value":0},"TopSurface":{"type":"Enum","value":{"enumType":"SurfaceType","value":"SmoothNoOutlines"}},"Transparency":{"type":"float","value":0}},"referenceId":"0004841f-97f1-2b45-83bb-00005b3b2a24"},{"className":"Weld","name":"Weld","parentId":"0004841f-97f1-2b45-83bb-00005b3b2a24","path":"ServerStorage.Maps.Desert.voxels.12347.Weld","properties":{"C0":{"type":"CFrame","value":{"position":[0,-0.5,0],"rotation":[1,0,0,0,0,-1,0,1,0]}},"C1":{"type":"CFrame","value":{"position":[-75.5,0.5,-28.5],"rotation":[1,0,0,0,0,-1,0,1,0]}},"Capabilities":{"type":"Enum","value":{"enumType":"SecurityCapabilities","value":""}},"Enabled":{"type":"bool","value":true},"Part0":{"type":"Enum","value":{"enumType":"BasePart","value":"12347"}},"Part1":{"type":"Enum","value":{"enumType":"BasePart","value":"PlayerSpawn"}}},"referenceId":"00048420-7045-5523-c07e-00001b62b289"},{"className":"Part","name":"12464","parentId":"00042e25-5c6f-3ac7-7e1f-00004cddd851","path":"ServerStorage.Maps.Desert.voxels.12464","properties":{"Anchored":{"type":"bool","value":true},"AudioCanCollide":{"type":"bool","value":true},"BackSurface":{"type":"Enum","value":{"enumType":"SurfaceType","value":"Smooth"}},"BottomSurface":{"type":"Enum","value":{"enumType":"SurfaceType","value":"SmoothNoOutlines"}},"CFrame":{"type":"CFrame","value":{"position":[49,0.5,213],"rotation":[1,0,0,0,1,0,0,0,1]}},"CanCollide":{"type":"bool","value":true},"CanQuery":{"type":"bool","value":true},"CanTouch":{"type":"bool","value":true},"Capabilities":{"type":"Enum","value":{"enumType":"SecurityCapabilities","value":""}},"CastShadow":{"type":"bool","value":false},"CollisionGroup":{"type":"string","value":"Default"},"CollisionGroupId":{"type":"int","value":0},"CustomPhysicalProperties":{"type":"nil"},"EnableFluidForces":{"type":"bool","value":true},"FrontSurface":{"type":"Enum","value":{"enumType":"SurfaceType","value":"Smooth"}},"LeftSurface":{"type":"Enum","value":{"enumType":"SurfaceType","value":"Smooth"}},"Locked":{"type":"bool","value":false},"Massless":{"type":"bool","value":false},"Material":{"type":"Enum","value":{"enumType":"Material","value":"Plastic"}},"PivotOffset":{"type":"CFrame","value":{"position":[0,0,0],"rotation":[1,0,0,0,1,0,0,0,1]}},"Reflectance":{"type":"float","value":0},"RightSurface":{"type":"Enum","value":{"enumType":"SurfaceType","value":"Smooth"}},"RootPriority":{"type":"int","value":0},"TopSurface":{"type":"Enum","value":{"enumType":"SurfaceType","value":"SmoothNoOutlines"}},"Transparency":{"type":"float","value":0}},"referenceId":"00048421-b58b-22fc-d5ab-00004c69bef2"},{"className":"Part","name":"12470","parentId":"00042e25-5c6f-3ac7-7e1f-00004cddd851","path":"ServerStorage.Maps.Desert.voxels.12470","properties":{"Anchored":{"type":"bool","value":true},"AudioCanCollide":{"type":"bool","value":true},"BackSurface":{"type":"Enum","value":{"enumType":"SurfaceType","value":"Smooth"}},"BottomSurface":{"type":"Enum","value":{"enumType":"SurfaceType","value":"SmoothNoOutlines"}},"CFrame":{"type":"CFrame","value":{"position":[49,0.5,219],"rotation":[1,0,0,0,1,0,0,0,1]}},"CanCollide":{"type":"bool","value":true},"CanQuery":{"type":"bool","value":true},"CanTouch":{"type":"bool","value":true},"Capabilities":{"type":"Enum","value":{"enumType":"SecurityCapabilities","value":""}},"CastShadow":{"type":"bool","value":false},"CollisionGroup":{"type":"string","value":"Default"},"CollisionGroupId":{"type":"int","value":0},"CustomPhysicalProperties":{"type":"nil"},"EnableFluidForces":{"type":"bool","value":true},"FrontSurface":{"type":"Enum","value":{"enumType":"SurfaceType","value":"Smooth"}},"LeftSurface":{"type":"Enum","value":{"enumType":"SurfaceType","value":"Smooth"}},"Locked":{"type":"bool","value":false},"Massless":{"type":"bool","value":false},"Material":{"type":"Enum","value":{"enumType":"Material","value":"Plastic"}},"PivotOffset":{"type":"CFrame","value":{"position":[0,0,0],"rotation":[1,0,0,0,1,0,0,0,1]}},"Reflectance":{"type":"float","value":0},"RightSurface":{"type":"Enum","value":{"enumType":"SurfaceType","value":"Smooth"}},"RootPriority":{"type":"int","value":0},"TopSurface":{"type":"Enum","value":{"enumType":"SurfaceType","value":"SmoothNoOutlines"}},"Transparency":{"type":"float","value":0}},"referenceId":"00048422-e03d-23b8-5efd-000067c348a8"},{"className":"Part","name":"12410","parentId":"00042e25-5c6f-3ac7-7e1f-00004cddd851","path":"ServerStorage.Maps.Desert.voxels.12410","properties":{"Anchored":{"type":"bool","value":true},"AudioCanCollide":{"type":"bool","value":true},"BackSurface":{"type":"Enum","value":{"enumType":"SurfaceType","value":"Smooth"}},"BottomSurface":{"type":"Enum","value":{"enumType":"SurfaceType","value":"SmoothNoOutlines"}},"CFrame":{"type":"CFrame","value":{"position":[49,1,159],"rotation":[1,0,0,0,1,0,0,0,1]}},"CanCollide":{"type":"bool","value":true},"CanQuery":{"type":"bool","value":true},"CanTouch":{"type":"bool","value":true},"Capabilities":{"type":"Enum","value":{"enumType":"SecurityCapabilities","value":""}},"CastShadow":{"type":"bool","value":true},"CollisionGroup":{"type":"string","value":"Default"},"CollisionGroupId":{"type":"int","value":0},"CustomPhysicalProperties":{"type":"nil"},"EnableFluidForces":{"type":"bool","value":true},"FrontSurface":{"type":"Enum","value":{"enumType":"SurfaceType","value":"Smooth"}},"LeftSurface":{"type":"Enum","value":{"enumType":"SurfaceType","value":"Smooth"}},"Locked":{"type":"bool","value":false},"Massless":{"type":"bool","value":false},"Material":{"type":"Enum","value":{"enumType":"Material","value":"Concrete"}},"PivotOffset":{"type":"CFrame","value":{"position":[0,0,0],"rotation":[1,0,0,0,1,0,0,0,1]}},"Reflectance":{"type":"float","value":0},"RightSurface":{"type":"Enum","value":{"enumType":"SurfaceType","value":"Smooth"}},"RootPriority":{"type":"int","value":0},"TopSurface":{"type":"Enum","value":{"enumType":"SurfaceType","value":"SmoothNoOutlines"}},"Transparency":{"type":"float","value":0}},"referenceId":"00048423-a9b6-8aac-30bd-0000302daa39"},{"className":"Weld","name":"Weld","parentId":"00048423-a9b6-8aac-30bd-0000302daa39","path":"ServerStorage.Maps.Desert.voxels.12410.Weld","properties":{"C0":{"type":"CFrame","value":{"position":[0,-0.5,0],"rotation":[1,0,0,0,0,-1,0,1,0]}},"C1":{"type":"CFrame","value":{"position":[-75.5,0.5,34.5],"rotation":[1,0,0,0,0,-1,0,1,0]}},"Capabilities":{"type":"Enum","value":{"enumType":"SecurityCapabilities","value":""}},"Enabled":{"type":"bool","value":true},"Part0":{"type":"Enum","value":{"enumType":"BasePart","value":"12410"}},"Part1":{"type":"Enum","value":{"enumType":"BasePart","value":"PlayerSpawn"}}},"referenceId":"00048424-fd27-a98b-0a08-00000c526206"},{"className":"Part","name":"12413","parentId":"00042e25-5c6f-3ac7-7e1f-00004cddd851","path":"ServerStorage.Maps.Desert.voxels.12413","properties":{"Anchored":{"type":"bool","value":true},"AudioCanCollide":{"type":"bool","value":true},"BackSurface":{"type":"Enum","value":{"enumType":"SurfaceType","value":"Smooth"}},"BottomSurface":{"type":"Enum","value":{"enumType":"SurfaceType","value":"SmoothNoOutlines"}},"CFrame":{"type":"CFrame","value":{"position":[49,1,162],"rotation":[1,0,0,0,1,0,0,0,1]}},"CanCollide":{"type":"bool","value":true},"CanQuery":{"type":"bool","value":true},"CanTouch":{"type":"bool","value":true},"Capabilities":{"type":"Enum","value":{"enumType":"SecurityCapabilities","value":""}},"CastShadow":{"type":"bool","value":true},"CollisionGroup":{"type":"string","value":"Default"},"CollisionGroupId":{"type":"int","value":0},"CustomPhysicalProperties":{"type":"nil"},"EnableFluidForces":{"type":"bool","value":true},"FrontSurface":{"type":"Enum","value":{"enumType":"SurfaceType","value":"Smooth"}},"LeftSurface":{"type":"Enum","value":{"enumType":"SurfaceType","value":"Smooth"}},"Locked":{"type":"bool","value":false},"Massless":{"type":"bool","value":false},"Material":{"type":"Enum","value":{"enumType":"Material","value":"Concrete"}},"PivotOffset":{"type":"CFrame","value":{"position":[0,0,0],"rotation":[1,0,0,0,1,0,0,0,1]}},"Reflectance":{"type":"float","value":0},"RightSurface":{"type":"Enum","value":{"enumType":"SurfaceType","value":"Smooth"}},"RootPriority":{"type":"int","value":0},"TopSurface":{"type":"Enum","value":{"enumType":"SurfaceType","value":"SmoothNoOutlines"}},"Transparency":{"type":"float","value":0}},"referenceId":"00048425-cf03-7000-9ba3-000013268a94"},{"className":"Weld","name":"Weld","parentId":"00048425-cf03-7000-9ba3-000013268a94","path":"ServerStorage.Maps.Desert.voxels.12413.Weld","properties":{"C0":{"type":"CFrame","value":{"position":[0,-0.5,0],"rotation":[1,0,0,0,0,-1,0,1,0]}},"C1":{"type":"CFrame","value":{"position":[-75.5,0.5,37.5],"rotation":[1,0,0,0,0,-1,0,1,0]}},"Capabilities":{"type":"Enum","value":{"enumType":"SecurityCapabilities","value":""}},"Enabled":{"type":"bool","value":true},"Part0":{"type":"Enum","value":{"enumType":"BasePart","value":"12413"}},"Part1":{"type":"Enum","value":{"enumType":"BasePart","value":"PlayerSpawn"}}},"referenceId":"00048426-dff8-57ca-5ad7-00003ca48817"},{"className":"Part","name":"12415","parentId":"00042e25-5c6f-3ac7-7e1f-00004cddd851","path":"ServerStorage.Maps.Desert.voxels.12415","properties":{"Anchored":{"type":"bool","value":true},"AudioCanCollide":{"type":"bool","value":true},"BackSurface":{"type":"Enum","value":{"enumType":"SurfaceType","value":"Smooth"}},"BottomSurface":{"type":"Enum","value":{"enumType":"SurfaceType","value":"SmoothNoOutlines"}},"CFrame":{"type":"CFrame","value":{"position":[49,1,164],"rotation":[1,0,0,0,1,0,0,0,1]}},"CanCollide":{"type":"bool","value":true},"CanQuery":{"type":"bool","value":true},"CanTouch":{"type":"bool","value":true},"Capabilities":{"type":"Enum","value":{"enumType":"SecurityCapabilities","value":""}},"CastShadow":{"type":"bool","value":true},"CollisionGroup":{"type":"string","value":"Default"},"CollisionGroupId":{"type":"int","value":0},"CustomPhysicalProperties":{"type":"nil"},"EnableFluidForces":{"type":"bool","value":true},"FrontSurface":{"type":"Enum","value":{"enumType":"SurfaceType","value":"Smooth"}},"LeftSurface":{"type":"Enum","value":{"enumType":"SurfaceType","value":"Smooth"}},"Locked":{"type":"bool","value":false},"Massless":{"type":"bool","value":false},"Material":{"type":"Enum","value":{"enumType":"Material","value":"Concrete"}},"PivotOffset":{"type":"CFrame","value":{"position":[0,0,0],"rotation":[1,0,0,0,1,0,0,0,1]}},"Reflectance":{"type":"float","value":0},"RightSurface":{"type":"Enum","value":{"enumType":"SurfaceType","value":"Smooth"}},"RootPriority":{"type":"int","value":0},"TopSurface":{"type":"Enum","value":{"enumType":"SurfaceType","value":"SmoothNoOutlines"}},"Transparency":{"type":"float","value":0}},"referenceId":"00048427-7d0e-2602-0818-0000715c27ee"},{"className":"Weld","name":"Weld","parentId":"00048427-7d0e-2602-0818-0000715c27ee","path":"ServerStorage.Maps.Desert.voxels.12415.Weld","properties":{"C0":{"type":"CFrame","value":{"position":[0,-0.5,0],"rotation":[1,0,0,0,0,-1,0,1,0]}},"C1":{"type":"CFrame","value":{"position":[-75.5,0.5,39.5],"rotation":[1,0,0,0,0,-1,0,1,0]}},"Capabilities":{"type":"Enum","value":{"enumType":"SecurityCapabilities","value":""}},"Enabled":{"type":"bool","value":true},"Part0":{"type":"Enum","value":{"enumType":"BasePart","value":"12415"}},"Part1":{"type":"Enum","value":{"enumType":"BasePart","value":"PlayerSpawn"}}},"referenceId":"00048428-464f-0c66-61e1-000027ef8464"},{"className":"Part","name":"12305","parentId":"00042e25-5c6f-3ac7-7e1f-00004cddd851","path":"ServerStorage.Maps.Desert.voxels.12305","properties":{"Anchored":{"type":"bool","value":true},"AudioCanCollide":{"type":"bool","value":true},"BackSurface":{"type":"Enum","value":{"enumType":"SurfaceType","value":"Smooth"}},"BottomSurface":{"type":"Enum","value":{"enumType":"SurfaceType","value":"SmoothNoOutlines"}},"CFrame":{"type":"CFrame","value":{"position":[49,1,54],"rotation":[1,0,0,0,1,0,0,0,1]}},"CanCollide":{"type":"bool","value":true},"CanQuery":{"type":"bool","value":true},"CanTouch":{"type":"bool","value":true},"Capabilities":{"type":"Enum","value":{"enumType":"SecurityCapabilities","value":""}},"CastShadow":{"type":"bool","value":true},"CollisionGroup":{"type":"string","value":"Default"},"CollisionGroupId":{"type":"int","value":0},"CustomPhysicalProperties":{"type":"nil"},"EnableFluidForces":{"type":"bool","value":true},"FrontSurface":{"type":"Enum","value":{"enumType":"SurfaceType","value":"Smooth"}},"LeftSurface":{"type":"Enum","value":{"enumType":"SurfaceType","value":"Smooth"}},"Locked":{"type":"bool","value":false},"Massless":{"type":"bool","value":false},"Material":{"type":"Enum","value":{"enumType":"Material","value":"Concrete"}},"PivotOffset":{"type":"CFrame","value":{"position":[0,0,0],"rotation":[1,0,0,0,1,0,0,0,1]}},"Reflectance":{"type":"float","value":0},"RightSurface":{"type":"Enum","value":{"enumType":"SurfaceType","value":"Smooth"}},"RootPriority":{"type":"int","value":0},"TopSurface":{"type":"Enum","value":{"enumType":"SurfaceType","value":"SmoothNoOutlines"}},"Transparency":{"type":"float","value":0}},"referenceId":"00048429-e30f-3fb1-8995-00005e453007"},{"className":"Weld","name":"Weld","parentId":"00048429-e30f-3fb1-8995-00005e453007","path":"ServerStorage.Maps.Desert.voxels.12305.Weld","properties":{"C0":{"type":"CFrame","value":{"position":[0,-0.5,0],"rotation":[1,0,0,0,0,-1,0,1,0]}},"C1":{"type":"CFrame","value":{"position":[-75.5,0.5,-70.5],"rotation":[1,0,0,0,0,-1,0,1,0]}},"Capabilities":{"type":"Enum","value":{"enumType":"SecurityCapabilities","value":""}},"Enabled":{"type":"bool","value":true},"Part0":{"type":"Enum","value":{"enumType":"BasePart","value":"12305"}},"Part1":{"type":"Enum","value":{"enumType":"BasePart","value":"PlayerSpawn"}}},"referenceId":"0004842a-b037-26b2-8610-00007b4769a5"},{"className":"Part","name":"12319","parentId":"00042e25-5c6f-3ac7-7e1f-00004cddd851","path":"ServerStorage.Maps.Desert.voxels.12319","properties":{"Anchored":{"type":"bool","value":true},"AudioCanCollide":{"type":"bool","value":true},"BackSurface":{"type":"Enum","value":{"enumType":"SurfaceType","value":"Smooth"}},"BottomSurface":{"type":"Enum","value":{"enumType":"SurfaceType","value":"SmoothNoOutlines"}},"CFrame":{"type":"CFrame","value":{"position":[49,1,68],"rotation":[1,0,0,0,1,0,0,0,1]}},"CanCollide":{"type":"bool","value":true},"CanQuery":{"type":"bool","value":true},"CanTouch":{"type":"bool","value":true},"Capabilities":{"type":"Enum","value":{"enumType":"SecurityCapabilities","value":""}},"CastShadow":{"type":"bool","value":true},"CollisionGroup":{"type":"string","value":"Default"},"CollisionGroupId":{"type":"int","value":0},"CustomPhysicalProperties":{"type":"nil"},"EnableFluidForces":{"type":"bool","value":true},"FrontSurface":{"type":"Enum","value":{"enumType":"SurfaceType","value":"Smooth"}},"LeftSurface":{"type":"Enum","value":{"enumType":"SurfaceType","value":"Smooth"}},"Locked":{"type":"bool","value":false},"Massless":{"type":"bool","value":false},"Material":{"type":"Enum","value":{"enumType":"Material","value":"Concrete"}},"PivotOffset":{"type":"CFrame","value":{"position":[0,0,0],"rotation":[1,0,0,0,1,0,0,0,1]}},"Reflectance":{"type":"float","value":0},"RightSurface":{"type":"Enum","value":{"enumType":"SurfaceType","value":"Smooth"}},"RootPriority":{"type":"int","value":0},"TopSurface":{"type":"Enum","value":{"enumType":"SurfaceType","value":"SmoothNoOutlines"}},"Transparency":{"type":"float","value":0}},"referenceId":"0004842b-1d3a-2a83-29a4-000021a0298f"},{"className":"Weld","name":"Weld","parentId":"0004842b-1d3a-2a83-29a4-000021a0298f","path":"ServerStorage.Maps.Desert.voxels.12319.Weld","properties":{"C0":{"type":"CFrame","value":{"position":[0,-0.5,0],"rotation":[1,0,0,0,0,-1,0,1,0]}},"C1":{"type":"CFrame","value":{"position":[-75.5,0.5,-56.5],"rotation":[1,0,0,0,0,-1,0,1,0]}},"Capabilities":{"type":"Enum","value":{"enumType":"SecurityCapabilities","value":""}},"Enabled":{"type":"bool","value":true},"Part0":{"type":"Enum","value":{"enumType":"BasePart","value":"12319"}},"Part1":{"type":"Enum","value":{"enumType":"BasePart","value":"PlayerSpawn"}}},"referenceId":"0004842c-958c-c491-e515-0000086e8fdf"},{"className":"Part","name":"12449","parentId":"00042e25-5c6f-3ac7-7e1f-00004cddd851","path":"ServerStorage.Maps.Desert.voxels.12449","properties":{"Anchored":{"type":"bool","value":true},"AudioCanCollide":{"type":"bool","value":true},"BackSurface":{"type":"Enum","value":{"enumType":"SurfaceType","value":"Smooth"}},"BottomSurface":{"type":"Enum","value":{"enumType":"SurfaceType","value":"SmoothNoOutlines"}},"CFrame":{"type":"CFrame","value":{"position":[49,0.5,198],"rotation":[1,0,0,0,1,0,0,0,1]}},"CanCollide":{"type":"bool","value":true},"CanQuery":{"type":"bool","value":true},"CanTouch":{"type":"bool","value":true},"Capabilities":{"type":"Enum","value":{"enumType":"SecurityCapabilities","value":""}},"CastShadow":{"type":"bool","value":false},"CollisionGroup":{"type":"string","value":"Default"},"CollisionGroupId":{"type":"int","value":0},"CustomPhysicalProperties":{"type":"nil"},"EnableFluidForces":{"type":"bool","value":true},"FrontSurface":{"type":"Enum","value":{"enumType":"SurfaceType","value":"Smooth"}},"LeftSurface":{"type":"Enum","value":{"enumType":"SurfaceType","value":"Smooth"}},"Locked":{"type":"bool","value":false},"Massless":{"type":"bool","value":false},"Material":{"type":"Enum","value":{"enumType":"Material","value":"Plastic"}},"PivotOffset":{"type":"CFrame","value":{"position":[0,0,0],"rotation":[1,0,0,0,1,0,0,0,1]}},"Reflectance":{"type":"float","value":0},"RightSurface":{"type":"Enum","value":{"enumType":"SurfaceType","value":"Smooth"}},"RootPriority":{"type":"int","value":0},"TopSurface":{"type":"Enum","value":{"enumType":"SurfaceType","value":"SmoothNoOutlines"}},"Transparency":{"type":"float","value":0}},"referenceId":"0004842d-aafa-3004-ec12-00007a842a40"},{"className":"Part","name":"12473","parentId":"00042e25-5c6f-3ac7-7e1f-00004cddd851","path":"ServerStorage.Maps.Desert.voxels.12473","properties":{"Anchored":{"type":"bool","value":true},"AudioCanCollide":{"type":"bool","value":true},"BackSurface":{"type":"Enum","value":{"enumType":"SurfaceType","value":"Smooth"}},"BottomSurface":{"type":"Enum","value":{"enumType":"SurfaceType","value":"SmoothNoOutlines"}},"CFrame":{"type":"CFrame","value":{"position":[49,0.5,222],"rotation":[1,0,0,0,1,0,0,0,1]}},"CanCollide":{"type":"bool","value":true},"CanQuery":{"type":"bool","value":true},"CanTouch":{"type":"bool","value":true},"Capabilities":{"type":"Enum","value":{"enumType":"SecurityCapabilities","value":""}},"CastShadow":{"type":"bool","value":false},"CollisionGroup":{"type":"string","value":"Default"},"CollisionGroupId":{"type":"int","value":0},"CustomPhysicalProperties":{"type":"nil"},"EnableFluidForces":{"type":"bool","value":true},"FrontSurface":{"type":"Enum","value":{"enumType":"SurfaceType","value":"Smooth"}},"LeftSurface":{"type":"Enum","value":{"enumType":"SurfaceType","value":"Smooth"}},"Locked":{"type":"bool","value":false},"Massless":{"type":"bool","value":false},"Material":{"type":"Enum","value":{"enumType":"Material","value":"Plastic"}},"PivotOffset":{"type":"CFrame","value":{"position":[0,0,0],"rotation":[1,0,0,0,1,0,0,0,1]}},"Reflectance":{"type":"float","value":0},"RightSurface":{"type":"Enum","value":{"enumType":"SurfaceType","value":"Smooth"}},"RootPriority":{"type":"int","value":0},"TopSurface":{"type":"Enum","value":{"enumType":"SurfaceType","value":"SmoothNoOutlines"}},"Transparency":{"type":"float","value":0}},"referenceId":"0004842e-4ae2-72ac-97bf-0000718400bc"},{"className":"Part","name":"12408","parentId":"00042e25-5c6f-3ac7-7e1f-00004cddd851","path":"ServerStorage.Maps.Desert.voxels.12408","properties":{"Anchored":{"type":"bool","value":true},"AudioCanCollide":{"type":"bool","value":true},"BackSurface":{"type":"Enum","value":{"enumType":"SurfaceType","value":"Smooth"}},"BottomSurface":{"type":"Enum","value":{"enumType":"SurfaceType","value":"SmoothNoOutlines"}},"CFrame":{"type":"CFrame","value":{"position":[49,1,157],"rotation":[1,0,0,0,1,0,0,0,1]}},"CanCollide":{"type":"bool","value":true},"CanQuery":{"type":"bool","value":true},"CanTouch":{"type":"bool","value":true},"Capabilities":{"type":"Enum","value":{"enumType":"SecurityCapabilities","value":""}},"CastShadow":{"type":"bool","value":true},"CollisionGroup":{"type":"string","value":"Default"},"CollisionGroupId":{"type":"int","value":0},"CustomPhysicalProperties":{"type":"nil"},"EnableFluidForces":{"type":"bool","value":true},"FrontSurface":{"type":"Enum","value":{"enumType":"SurfaceType","value":"Smooth"}},"LeftSurface":{"type":"Enum","value":{"enumType":"SurfaceType","value":"Smooth"}},"Locked":{"type":"bool","value":false},"Massless":{"type":"bool","value":false},"Material":{"type":"Enum","value":{"enumType":"Material","value":"Concrete"}},"PivotOffset":{"type":"CFrame","value":{"position":[0,0,0],"rotation":[1,0,0,0,1,0,0,0,1]}},"Reflectance":{"type":"float","value":0},"RightSurface":{"type":"Enum","value":{"enumType":"SurfaceType","value":"Smooth"}},"RootPriority":{"type":"int","value":0},"TopSurface":{"type":"Enum","value":{"enumType":"SurfaceType","value":"SmoothNoOutlines"}},"Transparency":{"type":"float","value":0}},"referenceId":"0004842f-e442-ae7c-36bc-00004a524759"},{"className":"Weld","name":"Weld","parentId":"0004842f-e442-ae7c-36bc-00004a524759","path":"ServerStorage.Maps.Desert.voxels.12408.Weld","properties":{"C0":{"type":"CFrame","value":{"position":[0,-0.5,0],"rotation":[1,0,0,0,0,-1,0,1,0]}},"C1":{"type":"CFrame","value":{"position":[-75.5,0.5,32.5],"rotation":[1,0,0,0,0,-1,0,1,0]}},"Capabilities":{"type":"Enum","value":{"enumType":"SecurityCapabilities","value":""}},"Enabled":{"type":"bool","value":true},"Part0":{"type":"Enum","value":{"enumType":"BasePart","value":"12408"}},"Part1":{"type":"Enum","value":{"enumType":"BasePart","value":"PlayerSpawn"}}},"referenceId":"00048430-b252-cf60-f84a-0000530ae280"},{"className":"Part","name":"12498","parentId":"00042e25-5c6f-3ac7-7e1f-00004cddd851","path":"ServerStorage.Maps.Desert.voxels.12498","properties":{"Anchored":{"type":"bool","value":true},"AudioCanCollide":{"type":"bool","value":true},"BackSurface":{"type":"Enum","value":{"enumType":"SurfaceType","value":"Smooth"}},"BottomSurface":{"type":"Enum","value":{"enumType":"SurfaceType","value":"SmoothNoOutlines"}},"CFrame":{"type":"CFrame","value":{"position":[49,1,247],"rotation":[1,0,0,0,1,0,0,0,1]}},"CanCollide":{"type":"bool","value":true},"CanQuery":{"type":"bool","value":true},"CanTouch":{"type":"bool","value":true},"Capabilities":{"type":"Enum","value":{"enumType":"SecurityCapabilities","value":""}},"CastShadow":{"type":"bool","value":true},"CollisionGroup":{"type":"string","value":"Default"},"CollisionGroupId":{"type":"int","value":0},"CustomPhysicalProperties":{"type":"nil"},"EnableFluidForces":{"type":"bool","value":true},"FrontSurface":{"type":"Enum","value":{"enumType":"SurfaceType","value":"Smooth"}},"LeftSurface":{"type":"Enum","value":{"enumType":"SurfaceType","value":"Smooth"}},"Locked":{"type":"bool","value":false},"Massless":{"type":"bool","value":false},"Material":{"type":"Enum","value":{"enumType":"Material","value":"Concrete"}},"PivotOffset":{"type":"CFrame","value":{"position":[0,0,0],"rotation":[1,0,0,0,1,0,0,0,1]}},"Reflectance":{"type":"float","value":0},"RightSurface":{"type":"Enum","value":{"enumType":"SurfaceType","value":"Smooth"}},"RootPriority":{"type":"int","value":0},"TopSurface":{"type":"Enum","value":{"enumType":"SurfaceType","value":"SmoothNoOutlines"}},"Transparency":{"type":"float","value":0}},"referenceId":"00048431-d05c-7c72-4f15-0000770100cd"},{"className":"Weld","name":"Weld","parentId":"00048431-d05c-7c72-4f15-0000770100cd","path":"ServerStorage.Maps.Desert.voxels.12498.Weld","properties":{"C0":{"type":"CFrame","value":{"position":[0,-0.5,0],"rotation":[1,0,0,0,0,-1,0,1,0]}},"C1":{"type":"CFrame","value":{"position":[-75.5,0.5,122.5],"rotation":[1,0,0,0,0,-1,0,1,0]}},"Capabilities":{"type":"Enum","value":{"enumType":"SecurityCapabilities","value":""}},"Enabled":{"type":"bool","value":true},"Part0":{"type":"Enum","value":{"enumType":"BasePart","value":"12498"}},"Part1":{"type":"Enum","value":{"enumType":"BasePart","value":"PlayerSpawn"}}},"referenceId":"00048432-c3bb-fac9-42a4-00004e8ac5c0"},{"className":"Part","name":"12370","parentId":"00042e25-5c6f-3ac7-7e1f-00004cddd851","path":"ServerStorage.Maps.Desert.voxels.12370","properties":{"Anchored":{"type":"bool","value":true},"AudioCanCollide":{"type":"bool","value":true},"BackSurface":{"type":"Enum","value":{"enumType":"SurfaceType","value":"Smooth"}},"BottomSurface":{"type":"Enum","value":{"enumType":"SurfaceType","value":"SmoothNoOutlines"}},"CFrame":{"type":"CFrame","value":{"position":[49,1,119],"rotation":[1,0,0,0,1,0,0,0,1]}},"CanCollide":{"type":"bool","value":true},"CanQuery":{"type":"bool","value":true},"CanTouch":{"type":"bool","value":true},"Capabilities":{"type":"Enum","value":{"enumType":"SecurityCapabilities","value":""}},"CastShadow":{"type":"bool","value":true},"CollisionGroup":{"type":"string","value":"Default"},"CollisionGroupId":{"type":"int","value":0},"CustomPhysicalProperties":{"type":"nil"},"EnableFluidForces":{"type":"bool","value":true},"FrontSurface":{"type":"Enum","value":{"enumType":"SurfaceType","value":"Smooth"}},"LeftSurface":{"type":"Enum","value":{"enumType":"SurfaceType","value":"Smooth"}},"Locked":{"type":"bool","value":false},"Massless":{"type":"bool","value":false},"Material":{"type":"Enum","value":{"enumType":"Material","value":"Concrete"}},"PivotOffset":{"type":"CFrame","value":{"position":[0,0,0],"rotation":[1,0,0,0,1,0,0,0,1]}},"Reflectance":{"type":"float","value":0},"RightSurface":{"type":"Enum","value":{"enumType":"SurfaceType","value":"Smooth"}},"RootPriority":{"type":"int","value":0},"TopSurface":{"type":"Enum","value":{"enumType":"SurfaceType","value":"SmoothNoOutlines"}},"Transparency":{"type":"float","value":0}},"referenceId":"00048433-b38f-7454-cb69-0000792974fb"},{"className":"Weld","name":"Weld","parentId":"00048433-b38f-7454-cb69-0000792974fb","path":"ServerStorage.Maps.Desert.voxels.12370.Weld","properties":{"C0":{"type":"CFrame","value":{"position":[0,-0.5,0],"rotation":[1,0,0,0,0,-1,0,1,0]}},"C1":{"type":"CFrame","value":{"position":[-75.5,0.5,-5.5],"rotation":[1,0,0,0,0,-1,0,1,0]}},"Capabilities":{"type":"Enum","value":{"enumType":"SecurityCapabilities","value":""}},"Enabled":{"type":"bool","value":true},"Part0":{"type":"Enum","value":{"enumType":"BasePart","value":"12370"}},"Part1":{"type":"Enum","value":{"enumType":"BasePart","value":"PlayerSpawn"}}},"referenceId":"00048434-9e09-d27f-4a5a-000001dcc262"},{"className":"Part","name":"12439","parentId":"00042e25-5c6f-3ac7-7e1f-00004cddd851","path":"ServerStorage.Maps.Desert.voxels.12439","properties":{"Anchored":{"type":"bool","value":true},"AudioCanCollide":{"type":"bool","value":true},"BackSurface":{"type":"Enum","value":{"enumType":"SurfaceType","value":"Smooth"}},"BottomSurface":{"type":"Enum","value":{"enumType":"SurfaceType","value":"SmoothNoOutlines"}},"CFrame":{"type":"CFrame","value":{"position":[49,1,188],"rotation":[1,0,0,0,1,0,0,0,1]}},"CanCollide":{"type":"bool","value":true},"CanQuery":{"type":"bool","value":true},"CanTouch":{"type":"bool","value":true},"Capabilities":{"type":"Enum","value":{"enumType":"SecurityCapabilities","value":""}},"CastShadow":{"type":"bool","value":true},"CollisionGroup":{"type":"string","value":"Default"},"CollisionGroupId":{"type":"int","value":0},"CustomPhysicalProperties":{"type":"nil"},"EnableFluidForces":{"type":"bool","value":true},"FrontSurface":{"type":"Enum","value":{"enumType":"SurfaceType","value":"Smooth"}},"LeftSurface":{"type":"Enum","value":{"enumType":"SurfaceType","value":"Smooth"}},"Locked":{"type":"bool","value":false},"Massless":{"type":"bool","value":false},"Material":{"type":"Enum","value":{"enumType":"Material","value":"Concrete"}},"PivotOffset":{"type":"CFrame","value":{"position":[0,0,0],"rotation":[1,0,0,0,1,0,0,0,1]}},"Reflectance":{"type":"float","value":0},"RightSurface":{"type":"Enum","value":{"enumType":"SurfaceType","value":"Smooth"}},"RootPriority":{"type":"int","value":0},"TopSurface":{"type":"Enum","value":{"enumType":"SurfaceType","value":"SmoothNoOutlines"}},"Transparency":{"type":"float","value":0}},"referenceId":"00048435-1825-a3aa-d598-00002071b0d5"},{"className":"Weld","name":"Weld","parentId":"00048435-1825-a3aa-d598-00002071b0d5","path":"ServerStorage.Maps.Desert.voxels.12439.Weld","properties":{"C0":{"type":"CFrame","value":{"position":[0,-0.5,0],"rotation":[1,0,0,0,0,-1,0,1,0]}},"C1":{"type":"CFrame","value":{"position":[-75.5,0.5,63.5],"rotation":[1,0,0,0,0,-1,0,1,0]}},"Capabilities":{"type":"Enum","value":{"enumType":"SecurityCapabilities","value":""}},"Enabled":{"type":"bool","value":true},"Part0":{"type":"Enum","value":{"enumType":"BasePart","value":"12439"}},"Part1":{"type":"Enum","value":{"enumType":"BasePart","value":"PlayerSpawn"}}},"referenceId":"00048436-6f28-9001-f014-00001223f540"},{"className":"Part","name":"12423","parentId":"00042e25-5c6f-3ac7-7e1f-00004cddd851","path":"ServerStorage.Maps.Desert.voxels.12423","properties":{"Anchored":{"type":"bool","value":true},"AudioCanCollide":{"type":"bool","value":true},"BackSurface":{"type":"Enum","value":{"enumType":"SurfaceType","value":"Smooth"}},"BottomSurface":{"type":"Enum","value":{"enumType":"SurfaceType","value":"SmoothNoOutlines"}},"CFrame":{"type":"CFrame","value":{"position":[49,1,172],"rotation":[1,0,0,0,1,0,0,0,1]}},"CanCollide":{"type":"bool","value":true},"CanQuery":{"type":"bool","value":true},"CanTouch":{"type":"bool","value":true},"Capabilities":{"type":"Enum","value":{"enumType":"SecurityCapabilities","value":""}},"CastShadow":{"type":"bool","value":true},"CollisionGroup":{"type":"string","value":"Default"},"CollisionGroupId":{"type":"int","value":0},"CustomPhysicalProperties":{"type":"nil"},"EnableFluidForces":{"type":"bool","value":true},"FrontSurface":{"type":"Enum","value":{"enumType":"SurfaceType","value":"Smooth"}},"LeftSurface":{"type":"Enum","value":{"enumType":"SurfaceType","value":"Smooth"}},"Locked":{"type":"bool","value":false},"Massless":{"type":"bool","value":false},"Material":{"type":"Enum","value":{"enumType":"Material","value":"Concrete"}},"PivotOffset":{"type":"CFrame","value":{"position":[0,0,0],"rotation":[1,0,0,0,1,0,0,0,1]}},"Reflectance":{"type":"float","value":0},"RightSurface":{"type":"Enum","value":{"enumType":"SurfaceType","value":"Smooth"}},"RootPriority":{"type":"int","value":0},"TopSurface":{"type":"Enum","value":{"enumType":"SurfaceType","value":"SmoothNoOutlines"}},"Transparency":{"type":"float","value":0}},"referenceId":"00048437-1bb7-8b1b-b194-00004307f9d8"},{"className":"Weld","name":"Weld","parentId":"00048437-1bb7-8b1b-b194-00004307f9d8","path":"ServerStorage.Maps.Desert.voxels.12423.Weld","properties":{"C0":{"type":"CFrame","value":{"position":[0,-0.5,0],"rotation":[1,0,0,0,0,-1,0,1,0]}},"C1":{"type":"CFrame","value":{"position":[-75.5,0.5,47.5],"rotation":[1,0,0,0,0,-1,0,1,0]}},"Capabilities":{"type":"Enum","value":{"enumType":"SecurityCapabilities","value":""}},"Enabled":{"type":"bool","value":true},"Part0":{"type":"Enum","value":{"enumType":"BasePart","value":"12423"}},"Part1":{"type":"Enum","value":{"enumType":"BasePart","value":"PlayerSpawn"}}},"referenceId":"00048438-f386-4f22-93a3-00003da3cc33"},{"className":"Part","name":"12322","parentId":"00042e25-5c6f-3ac7-7e1f-00004cddd851","path":"ServerStorage.Maps.Desert.voxels.12322","properties":{"Anchored":{"type":"bool","value":true},"AudioCanCollide":{"type":"bool","value":true},"BackSurface":{"type":"Enum","value":{"enumType":"SurfaceType","value":"Smooth"}},"BottomSurface":{"type":"Enum","value":{"enumType":"SurfaceType","value":"SmoothNoOutlines"}},"CFrame":{"type":"CFrame","value":{"position":[49,1,71],"rotation":[1,0,0,0,1,0,0,0,1]}},"CanCollide":{"type":"bool","value":true},"CanQuery":{"type":"bool","value":true},"CanTouch":{"type":"bool","value":true},"Capabilities":{"type":"Enum","value":{"enumType":"SecurityCapabilities","value":""}},"CastShadow":{"type":"bool","value":true},"CollisionGroup":{"type":"string","value":"Default"},"CollisionGroupId":{"type":"int","value":0},"CustomPhysicalProperties":{"type":"nil"},"EnableFluidForces":{"type":"bool","value":true},"FrontSurface":{"type":"Enum","value":{"enumType":"SurfaceType","value":"Smooth"}},"LeftSurface":{"type":"Enum","value":{"enumType":"SurfaceType","value":"Smooth"}},"Locked":{"type":"bool","value":false},"Massless":{"type":"bool","value":false},"Material":{"type":"Enum","value":{"enumType":"Material","value":"Concrete"}},"PivotOffset":{"type":"CFrame","value":{"position":[0,0,0],"rotation":[1,0,0,0,1,0,0,0,1]}},"Reflectance":{"type":"float","value":0},"RightSurface":{"type":"Enum","value":{"enumType":"SurfaceType","value":"Smooth"}},"RootPriority":{"type":"int","value":0},"TopSurface":{"type":"Enum","value":{"enumType":"SurfaceType","value":"SmoothNoOutlines"}},"Transparency":{"type":"float","value":0}},"referenceId":"00048439-41f4-8712-f4bc-0000292d2440"},{"className":"Weld","name":"Weld","parentId":"00048439-41f4-8712-f4bc-0000292d2440","path":"ServerStorage.Maps.Desert.voxels.12322.Weld","properties":{"C0":{"type":"CFrame","value":{"position":[0,-0.5,0],"rotation":[1,0,0,0,0,-1,0,1,0]}},"C1":{"type":"CFrame","value":{"position":[-75.5,0.5,-53.5],"rotation":[1,0,0,0,0,-1,0,1,0]}},"Capabilities":{"type":"Enum","value":{"enumType":"SecurityCapabilities","value":""}},"Enabled":{"type":"bool","value":true},"Part0":{"type":"Enum","value":{"enumType":"BasePart","value":"12322"}},"Part1":{"type":"Enum","value":{"enumType":"BasePart","value":"PlayerSpawn"}}},"referenceId":"0004843a-14b4-fe77-b6be-000072bd2dca"},{"className":"Part","name":"12368","parentId":"00042e25-5c6f-3ac7-7e1f-00004cddd851","path":"ServerStorage.Maps.Desert.voxels.12368","properties":{"Anchored":{"type":"bool","value":true},"AudioCanCollide":{"type":"bool","value":true},"BackSurface":{"type":"Enum","value":{"enumType":"SurfaceType","value":"Smooth"}},"BottomSurface":{"type":"Enum","value":{"enumType":"SurfaceType","value":"SmoothNoOutlines"}},"CFrame":{"type":"CFrame","value":{"position":[49,1,117],"rotation":[1,0,0,0,1,0,0,0,1]}},"CanCollide":{"type":"bool","value":true},"CanQuery":{"type":"bool","value":true},"CanTouch":{"type":"bool","value":true},"Capabilities":{"type":"Enum","value":{"enumType":"SecurityCapabilities","value":""}},"CastShadow":{"type":"bool","value":true},"CollisionGroup":{"type":"string","value":"Default"},"CollisionGroupId":{"type":"int","value":0},"CustomPhysicalProperties":{"type":"nil"},"EnableFluidForces":{"type":"bool","value":true},"FrontSurface":{"type":"Enum","value":{"enumType":"SurfaceType","value":"Smooth"}},"LeftSurface":{"type":"Enum","value":{"enumType":"SurfaceType","value":"Smooth"}},"Locked":{"type":"bool","value":false},"Massless":{"type":"bool","value":false},"Material":{"type":"Enum","value":{"enumType":"Material","value":"Concrete"}},"PivotOffset":{"type":"CFrame","value":{"position":[0,0,0],"rotation":[1,0,0,0,1,0,0,0,1]}},"Reflectance":{"type":"float","value":0},"RightSurface":{"type":"Enum","value":{"enumType":"SurfaceType","value":"Smooth"}},"RootPriority":{"type":"int","value":0},"TopSurface":{"type":"Enum","value":{"enumType":"SurfaceType","value":"SmoothNoOutlines"}},"Transparency":{"type":"float","value":0}},"referenceId":"0004843b-e3cb-ccee-c839-00007eb75ca0"},{"className":"Weld","name":"Weld","parentId":"0004843b-e3cb-ccee-c839-00007eb75ca0","path":"ServerStorage.Maps.Desert.voxels.12368.Weld","properties":{"C0":{"type":"CFrame","value":{"position":[0,-0.5,0],"rotation":[1,0,0,0,0,-1,0,1,0]}},"C1":{"type":"CFrame","value":{"position":[-75.5,0.5,-7.5],"rotation":[1,0,0,0,0,-1,0,1,0]}},"Capabilities":{"type":"Enum","value":{"enumType":"SecurityCapabilities","value":""}},"Enabled":{"type":"bool","value":true},"Part0":{"type":"Enum","value":{"enumType":"BasePart","value":"12368"}},"Part1":{"type":"Enum","value":{"enumType":"BasePart","value":"PlayerSpawn"}}},"referenceId":"0004843c-5bc6-6418-2a7c-00005e03c7d0"},{"className":"Part","name":"12381","parentId":"00042e25-5c6f-3ac7-7e1f-00004cddd851","path":"ServerStorage.Maps.Desert.voxels.12381","properties":{"Anchored":{"type":"bool","value":true},"AudioCanCollide":{"type":"bool","value":true},"BackSurface":{"type":"Enum","value":{"enumType":"SurfaceType","value":"Smooth"}},"BottomSurface":{"type":"Enum","value":{"enumType":"SurfaceType","value":"SmoothNoOutlines"}},"CFrame":{"type":"CFrame","value":{"position":[49,1,130],"rotation":[1,0,0,0,1,0,0,0,1]}},"CanCollide":{"type":"bool","value":true},"CanQuery":{"type":"bool","value":true},"CanTouch":{"type":"bool","value":true},"Capabilities":{"type":"Enum","value":{"enumType":"SecurityCapabilities","value":""}},"CastShadow":{"type":"bool","value":true},"CollisionGroup":{"type":"string","value":"Default"},"CollisionGroupId":{"type":"int","value":0},"CustomPhysicalProperties":{"type":"nil"},"EnableFluidForces":{"type":"bool","value":true},"FrontSurface":{"type":"Enum","value":{"enumType":"SurfaceType","value":"Smooth"}},"LeftSurface":{"type":"Enum","value":{"enumType":"SurfaceType","value":"Smooth"}},"Locked":{"type":"bool","value":false},"Massless":{"type":"bool","value":false},"Material":{"type":"Enum","value":{"enumType":"Material","value":"Concrete"}},"PivotOffset":{"type":"CFrame","value":{"position":[0,0,0],"rotation":[1,0,0,0,1,0,0,0,1]}},"Reflectance":{"type":"float","value":0},"RightSurface":{"type":"Enum","value":{"enumType":"SurfaceType","value":"Smooth"}},"RootPriority":{"type":"int","value":0},"TopSurface":{"type":"Enum","value":{"enumType":"SurfaceType","value":"SmoothNoOutlines"}},"Transparency":{"type":"float","value":0}},"referenceId":"0004843d-5d60-0fd2-6342-000069c04bd9"},{"className":"Weld","name":"Weld","parentId":"0004843d-5d60-0fd2-6342-000069c04bd9","path":"ServerStorage.Maps.Desert.voxels.12381.Weld","properties":{"C0":{"type":"CFrame","value":{"position":[0,-0.5,0],"rotation":[1,0,0,0,0,-1,0,1,0]}},"C1":{"type":"CFrame","value":{"position":[-75.5,0.5,5.5],"rotation":[1,0,0,0,0,-1,0,1,0]}},"Capabilities":{"type":"Enum","value":{"enumType":"SecurityCapabilities","value":""}},"Enabled":{"type":"bool","value":true},"Part0":{"type":"Enum","value":{"enumType":"BasePart","value":"12381"}},"Part1":{"type":"Enum","value":{"enumType":"BasePart","value":"PlayerSpawn"}}},"referenceId":"0004843e-d353-a762-f3bf-000023fd9cfc"},{"className":"Part","name":"12488","parentId":"00042e25-5c6f-3ac7-7e1f-00004cddd851","path":"ServerStorage.Maps.Desert.voxels.12488","properties":{"Anchored":{"type":"bool","value":true},"AudioCanCollide":{"type":"bool","value":true},"BackSurface":{"type":"Enum","value":{"enumType":"SurfaceType","value":"Smooth"}},"BottomSurface":{"type":"Enum","value":{"enumType":"SurfaceType","value":"SmoothNoOutlines"}},"CFrame":{"type":"CFrame","value":{"position":[49,1,237],"rotation":[1,0,0,0,1,0,0,0,1]}},"CanCollide":{"type":"bool","value":true},"CanQuery":{"type":"bool","value":true},"CanTouch":{"type":"bool","value":true},"Capabilities":{"type":"Enum","value":{"enumType":"SecurityCapabilities","value":""}},"CastShadow":{"type":"bool","value":true},"CollisionGroup":{"type":"string","value":"Default"},"CollisionGroupId":{"type":"int","value":0},"CustomPhysicalProperties":{"type":"nil"},"EnableFluidForces":{"type":"bool","value":true},"FrontSurface":{"type":"Enum","value":{"enumType":"SurfaceType","value":"Smooth"}},"LeftSurface":{"type":"Enum","value":{"enumType":"SurfaceType","value":"Smooth"}},"Locked":{"type":"bool","value":false},"Massless":{"type":"bool","value":false},"Material":{"type":"Enum","value":{"enumType":"Material","value":"Concrete"}},"PivotOffset":{"type":"CFrame","value":{"position":[0,0,0],"rotation":[1,0,0,0,1,0,0,0,1]}},"Reflectance":{"type":"float","value":0},"RightSurface":{"type":"Enum","value":{"enumType":"SurfaceType","value":"Smooth"}},"RootPriority":{"type":"int","value":0},"TopSurface":{"type":"Enum","value":{"enumType":"SurfaceType","value":"SmoothNoOutlines"}},"Transparency":{"type":"float","value":0}},"referenceId":"0004843f-bddf-a13e-4fbd-00001b0af596"},{"className":"Weld","name":"Weld","parentId":"0004843f-bddf-a13e-4fbd-00001b0af596","path":"ServerStorage.Maps.Desert.voxels.12488.Weld","properties":{"C0":{"type":"CFrame","value":{"position":[0,-0.5,0],"rotation":[1,0,0,0,0,-1,0,1,0]}},"C1":{"type":"CFrame","value":{"position":[-75.5,0.5,112.5],"rotation":[1,0,0,0,0,-1,0,1,0]}},"Capabilities":{"type":"Enum","value":{"enumType":"SecurityCapabilities","value":""}},"Enabled":{"type":"bool","value":true},"Part0":{"type":"Enum","value":{"enumType":"BasePart","value":"12488"}},"Part1":{"type":"Enum","value":{"enumType":"BasePart","value":"PlayerSpawn"}}},"referenceId":"00048440-f80b-2367-e938-00002f2a64eb"},{"className":"Part","name":"12475","parentId":"00042e25-5c6f-3ac7-7e1f-00004cddd851","path":"ServerStorage.Maps.Desert.voxels.12475","properties":{"Anchored":{"type":"bool","value":true},"AudioCanCollide":{"type":"bool","value":true},"BackSurface":{"type":"Enum","value":{"enumType":"SurfaceType","value":"Smooth"}},"BottomSurface":{"type":"Enum","value":{"enumType":"SurfaceType","value":"SmoothNoOutlines"}},"CFrame":{"type":"CFrame","value":{"position":[49,0.5,224],"rotation":[1,0,0,0,1,0,0,0,1]}},"CanCollide":{"type":"bool","value":true},"CanQuery":{"type":"bool","value":true},"CanTouch":{"type":"bool","value":true},"Capabilities":{"type":"Enum","value":{"enumType":"SecurityCapabilities","value":""}},"CastShadow":{"type":"bool","value":false},"CollisionGroup":{"type":"string","value":"Default"},"CollisionGroupId":{"type":"int","value":0},"CustomPhysicalProperties":{"type":"nil"},"EnableFluidForces":{"type":"bool","value":true},"FrontSurface":{"type":"Enum","value":{"enumType":"SurfaceType","value":"Smooth"}},"LeftSurface":{"type":"Enum","value":{"enumType":"SurfaceType","value":"Smooth"}},"Locked":{"type":"bool","value":false},"Massless":{"type":"bool","value":false},"Material":{"type":"Enum","value":{"enumType":"Material","value":"Plastic"}},"PivotOffset":{"type":"CFrame","value":{"position":[0,0,0],"rotation":[1,0,0,0,1,0,0,0,1]}},"Reflectance":{"type":"float","value":0},"RightSurface":{"type":"Enum","value":{"enumType":"SurfaceType","value":"Smooth"}},"RootPriority":{"type":"int","value":0},"TopSurface":{"type":"Enum","value":{"enumType":"SurfaceType","value":"SmoothNoOutlines"}},"Transparency":{"type":"float","value":0}},"referenceId":"00048441-3b53-4f90-5787-0000652b6366"}]