[{"className":"Weld","name":"Weld","parentId":"0002e889-707a-2203-24ae-00002d072bd0","path":"ServerStorage.Maps.Amazon.voxels.16896.Weld","properties":{"C0":{"type":"CFrame","value":{"position":[0,-0.5,0],"rotation":[1,0,0,0,0,-1,0,1,0]}},"C1":{"type":"CFrame","value":{"position":[-57.5,0.5,20.5],"rotation":[1,0,0,0,0,-1,0,1,0]}},"Capabilities":{"type":"Enum","value":{"enumType":"SecurityCapabilities","value":""}},"Enabled":{"type":"bool","value":true},"Part0":{"type":"Enum","value":{"enumType":"BasePart","value":"16896"}},"Part1":{"type":"Enum","value":{"enumType":"BasePart","value":"PlayerSpawn"}}},"referenceId":"0002e88a-ae31-46db-fc90-000070cc0ebf"},{"className":"Part","name":"16759","parentId":"00027302-b139-2950-51b5-00005b278fde","path":"ServerStorage.Maps.Amazon.voxels.16759","properties":{"Anchored":{"type":"bool","value":true},"AudioCanCollide":{"type":"bool","value":true},"BackSurface":{"type":"Enum","value":{"enumType":"SurfaceType","value":"Smooth"}},"BottomSurface":{"type":"Enum","value":{"enumType":"SurfaceType","value":"SmoothNoOutlines"}},"CFrame":{"type":"CFrame","value":{"position":[67,0.5,8],"rotation":[1,0,0,0,1,0,0,0,1]}},"CanCollide":{"type":"bool","value":true},"CanQuery":{"type":"bool","value":true},"CanTouch":{"type":"bool","value":true},"Capabilities":{"type":"Enum","value":{"enumType":"SecurityCapabilities","value":""}},"CastShadow":{"type":"bool","value":false},"CollisionGroup":{"type":"string","value":"Default"},"CollisionGroupId":{"type":"int","value":0},"CustomPhysicalProperties":{"type":"nil"},"EnableFluidForces":{"type":"bool","value":true},"FrontSurface":{"type":"Enum","value":{"enumType":"SurfaceType","value":"Smooth"}},"LeftSurface":{"type":"Enum","value":{"enumType":"SurfaceType","value":"Smooth"}},"Locked":{"type":"bool","value":false},"Massless":{"type":"bool","value":false},"Material":{"type":"Enum","value":{"enumType":"Material","value":"Plastic"}},"PivotOffset":{"type":"CFrame","value":{"position":[0,0,0],"rotation":[1,0,0,0,1,0,0,0,1]}},"Reflectance":{"type":"float","value":0},"RightSurface":{"type":"Enum","value":{"enumType":"SurfaceType","value":"Smooth"}},"RootPriority":{"type":"int","value":0},"TopSurface":{"type":"Enum","value":{"enumType":"SurfaceType","value":"SmoothNoOutlines"}},"Transparency":{"type":"float","value":0}},"referenceId":"0002e88b-ed29-b33e-c95f-00005fa95024"},{"className":"Part","name":"16873","parentId":"00027302-b139-2950-51b5-00005b278fde","path":"ServerStorage.Maps.Amazon.voxels.16873","properties":{"Anchored":{"type":"bool","value":true},"AudioCanCollide":{"type":"bool","value":true},"BackSurface":{"type":"Enum","value":{"enumType":"SurfaceType","value":"Smooth"}},"BottomSurface":{"type":"Enum","value":{"enumType":"SurfaceType","value":"SmoothNoOutlines"}},"CFrame":{"type":"CFrame","value":{"position":[67,1,122],"rotation":[1,0,0,0,1,0,0,0,1]}},"CanCollide":{"type":"bool","value":true},"CanQuery":{"type":"bool","value":true},"CanTouch":{"type":"bool","value":true},"Capabilities":{"type":"Enum","value":{"enumType":"SecurityCapabilities","value":""}},"CastShadow":{"type":"bool","value":true},"CollisionGroup":{"type":"string","value":"Default"},"CollisionGroupId":{"type":"int","value":0},"CustomPhysicalProperties":{"type":"nil"},"EnableFluidForces":{"type":"bool","value":true},"FrontSurface":{"type":"Enum","value":{"enumType":"SurfaceType","value":"Smooth"}},"LeftSurface":{"type":"Enum","value":{"enumType":"SurfaceType","value":"Smooth"}},"Locked":{"type":"bool","value":false},"Massless":{"type":"bool","value":false},"Material":{"type":"Enum","value":{"enumType":"Material","value":"Sand"}},"PivotOffset":{"type":"CFrame","value":{"position":[0,0,0],"rotation":[1,0,0,0,1,0,0,0,1]}},"Reflectance":{"type":"float","value":0},"RightSurface":{"type":"Enum","value":{"enumType":"SurfaceType","value":"Smooth"}},"RootPriority":{"type":"int","value":0},"TopSurface":{"type":"Enum","value":{"enumType":"SurfaceType","value":"SmoothNoOutlines"}},"Transparency":{"type":"float","value":0}},"referenceId":"0002e88c-c05d-2662-42b1-00001269572d"},{"className":"Weld","name":"Weld","parentId":"0002e88c-c05d-2662-42b1-00001269572d","path":"ServerStorage.Maps.Amazon.voxels.16873.Weld","properties":{"C0":{"type":"CFrame","value":{"position":[0,-0.5,0],"rotation":[1,0,0,0,0,-1,0,1,0]}},"C1":{"type":"CFrame","value":{"position":[-57.5,0.5,-2.5],"rotation":[1,0,0,0,0,-1,0,1,0]}},"Capabilities":{"type":"Enum","value":{"enumType":"SecurityCapabilities","value":""}},"Enabled":{"type":"bool","value":true},"Part0":{"type":"Enum","value":{"enumType":"BasePart","value":"16873"}},"Part1":{"type":"Enum","value":{"enumType":"BasePart","value":"PlayerSpawn"}}},"referenceId":"0002e88d-2f58-497a-abcc-00007f86ad7c"},{"className":"Part","name":"16923","parentId":"00027302-b139-2950-51b5-00005b278fde","path":"ServerStorage.Maps.Amazon.voxels.16923","properties":{"Anchored":{"type":"bool","value":true},"AudioCanCollide":{"type":"bool","value":true},"BackSurface":{"type":"Enum","value":{"enumType":"SurfaceType","value":"Smooth"}},"BottomSurface":{"type":"Enum","value":{"enumType":"SurfaceType","value":"SmoothNoOutlines"}},"CFrame":{"type":"CFrame","value":{"position":[67,1,172],"rotation":[1,0,0,0,1,0,0,0,1]}},"CanCollide":{"type":"bool","value":true},"CanQuery":{"type":"bool","value":true},"CanTouch":{"type":"bool","value":true},"Capabilities":{"type":"Enum","value":{"enumType":"SecurityCapabilities","value":""}},"CastShadow":{"type":"bool","value":true},"CollisionGroup":{"type":"string","value":"Default"},"CollisionGroupId":{"type":"int","value":0},"CustomPhysicalProperties":{"type":"nil"},"EnableFluidForces":{"type":"bool","value":true},"FrontSurface":{"type":"Enum","value":{"enumType":"SurfaceType","value":"Smooth"}},"LeftSurface":{"type":"Enum","value":{"enumType":"SurfaceType","value":"Smooth"}},"Locked":{"type":"bool","value":false},"Massless":{"type":"bool","value":false},"Material":{"type":"Enum","value":{"enumType":"Material","value":"Sand"}},"PivotOffset":{"type":"CFrame","value":{"position":[0,0,0],"rotation":[1,0,0,0,1,0,0,0,1]}},"Reflectance":{"type":"float","value":0},"RightSurface":{"type":"Enum","value":{"enumType":"SurfaceType","value":"Smooth"}},"RootPriority":{"type":"int","value":0},"TopSurface":{"type":"Enum","value":{"enumType":"SurfaceType","value":"SmoothNoOutlines"}},"Transparency":{"type":"float","value":0}},"referenceId":"0002e88e-6206-e97a-0e68-00005c6b30d8"},{"className":"Weld","name":"Weld","parentId":"0002e88e-6206-e97a-0e68-00005c6b30d8","path":"ServerStorage.Maps.Amazon.voxels.16923.Weld","properties":{"C0":{"type":"CFrame","value":{"position":[0,-0.5,0],"rotation":[1,0,0,0,0,-1,0,1,0]}},"C1":{"type":"CFrame","value":{"position":[-57.5,0.5,47.5],"rotation":[1,0,0,0,0,-1,0,1,0]}},"Capabilities":{"type":"Enum","value":{"enumType":"SecurityCapabilities","value":""}},"Enabled":{"type":"bool","value":true},"Part0":{"type":"Enum","value":{"enumType":"BasePart","value":"16923"}},"Part1":{"type":"Enum","value":{"enumType":"BasePart","value":"PlayerSpawn"}}},"referenceId":"0002e88f-fdd0-afa3-50e2-00005b50b8e4"},{"className":"Part","name":"16947","parentId":"00027302-b139-2950-51b5-00005b278fde","path":"ServerStorage.Maps.Amazon.voxels.16947","properties":{"Anchored":{"type":"bool","value":true},"AudioCanCollide":{"type":"bool","value":true},"BackSurface":{"type":"Enum","value":{"enumType":"SurfaceType","value":"Smooth"}},"BottomSurface":{"type":"Enum","value":{"enumType":"SurfaceType","value":"SmoothNoOutlines"}},"CFrame":{"type":"CFrame","value":{"position":[67,1,196],"rotation":[1,0,0,0,1,0,0,0,1]}},"CanCollide":{"type":"bool","value":true},"CanQuery":{"type":"bool","value":true},"CanTouch":{"type":"bool","value":true},"Capabilities":{"type":"Enum","value":{"enumType":"SecurityCapabilities","value":""}},"CastShadow":{"type":"bool","value":true},"CollisionGroup":{"type":"string","value":"Default"},"CollisionGroupId":{"type":"int","value":0},"CustomPhysicalProperties":{"type":"nil"},"EnableFluidForces":{"type":"bool","value":true},"FrontSurface":{"type":"Enum","value":{"enumType":"SurfaceType","value":"Smooth"}},"LeftSurface":{"type":"Enum","value":{"enumType":"SurfaceType","value":"Smooth"}},"Locked":{"type":"bool","value":false},"Massless":{"type":"bool","value":false},"Material":{"type":"Enum","value":{"enumType":"Material","value":"Sand"}},"PivotOffset":{"type":"CFrame","value":{"position":[0,0,0],"rotation":[1,0,0,0,1,0,0,0,1]}},"Reflectance":{"type":"float","value":0},"RightSurface":{"type":"Enum","value":{"enumType":"SurfaceType","value":"Smooth"}},"RootPriority":{"type":"int","value":0},"TopSurface":{"type":"Enum","value":{"enumType":"SurfaceType","value":"SmoothNoOutlines"}},"Transparency":{"type":"float","value":0}},"referenceId":"0002e890-def3-7777-e0b4-00005859fcb1"},{"className":"Weld","name":"Weld","parentId":"0002e890-def3-7777-e0b4-00005859fcb1","path":"ServerStorage.Maps.Amazon.voxels.16947.Weld","properties":{"C0":{"type":"CFrame","value":{"position":[0,-0.5,0],"rotation":[1,0,0,0,0,-1,0,1,0]}},"C1":{"type":"CFrame","value":{"position":[-57.5,0.5,71.5],"rotation":[1,0,0,0,0,-1,0,1,0]}},"Capabilities":{"type":"Enum","value":{"enumType":"SecurityCapabilities","value":""}},"Enabled":{"type":"bool","value":true},"Part0":{"type":"Enum","value":{"enumType":"BasePart","value":"16947"}},"Part1":{"type":"Enum","value":{"enumType":"BasePart","value":"PlayerSpawn"}}},"referenceId":"0002e891-95b7-8cd7-5bb5-00004e1e0094"},{"className":"Part","name":"16846","parentId":"00027302-b139-2950-51b5-00005b278fde","path":"ServerStorage.Maps.Amazon.voxels.16846","properties":{"Anchored":{"type":"bool","value":true},"AudioCanCollide":{"type":"bool","value":true},"BackSurface":{"type":"Enum","value":{"enumType":"SurfaceType","value":"Smooth"}},"BottomSurface":{"type":"Enum","value":{"enumType":"SurfaceType","value":"SmoothNoOutlines"}},"CFrame":{"type":"CFrame","value":{"position":[67,1,95],"rotation":[1,0,0,0,1,0,0,0,1]}},"CanCollide":{"type":"bool","value":true},"CanQuery":{"type":"bool","value":true},"CanTouch":{"type":"bool","value":true},"Capabilities":{"type":"Enum","value":{"enumType":"SecurityCapabilities","value":""}},"CastShadow":{"type":"bool","value":true},"CollisionGroup":{"type":"string","value":"Default"},"CollisionGroupId":{"type":"int","value":0},"CustomPhysicalProperties":{"type":"nil"},"EnableFluidForces":{"type":"bool","value":true},"FrontSurface":{"type":"Enum","value":{"enumType":"SurfaceType","value":"Smooth"}},"LeftSurface":{"type":"Enum","value":{"enumType":"SurfaceType","value":"Smooth"}},"Locked":{"type":"bool","value":false},"Massless":{"type":"bool","value":false},"Material":{"type":"Enum","value":{"enumType":"Material","value":"Sand"}},"PivotOffset":{"type":"CFrame","value":{"position":[0,0,0],"rotation":[1,0,0,0,1,0,0,0,1]}},"Reflectance":{"type":"float","value":0},"RightSurface":{"type":"Enum","value":{"enumType":"SurfaceType","value":"Smooth"}},"RootPriority":{"type":"int","value":0},"TopSurface":{"type":"Enum","value":{"enumType":"SurfaceType","value":"SmoothNoOutlines"}},"Transparency":{"type":"float","value":0}},"referenceId":"0002e892-f10b-58ce-9e1c-00007726e0e2"},{"className":"Weld","name":"Weld","parentId":"0002e892-f10b-58ce-9e1c-00007726e0e2","path":"ServerStorage.Maps.Amazon.voxels.16846.Weld","properties":{"C0":{"type":"CFrame","value":{"position":[0,-0.5,0],"rotation":[1,0,0,0,0,-1,0,1,0]}},"C1":{"type":"CFrame","value":{"position":[-57.5,0.5,-29.5],"rotation":[1,0,0,0,0,-1,0,1,0]}},"Capabilities":{"type":"Enum","value":{"enumType":"SecurityCapabilities","value":""}},"Enabled":{"type":"bool","value":true},"Part0":{"type":"Enum","value":{"enumType":"BasePart","value":"16846"}},"Part1":{"type":"Enum","value":{"enumType":"BasePart","value":"PlayerSpawn"}}},"referenceId":"0002e893-7a19-d944-d813-000075fc1fcc"},{"className":"Part","name":"16916","parentId":"00027302-b139-2950-51b5-00005b278fde","path":"ServerStorage.Maps.Amazon.voxels.16916","properties":{"Anchored":{"type":"bool","value":true},"AudioCanCollide":{"type":"bool","value":true},"BackSurface":{"type":"Enum","value":{"enumType":"SurfaceType","value":"Smooth"}},"BottomSurface":{"type":"Enum","value":{"enumType":"SurfaceType","value":"SmoothNoOutlines"}},"CFrame":{"type":"CFrame","value":{"position":[67,1,165],"rotation":[1,0,0,0,1,0,0,0,1]}},"CanCollide":{"type":"bool","value":true},"CanQuery":{"type":"bool","value":true},"CanTouch":{"type":"bool","value":true},"Capabilities":{"type":"Enum","value":{"enumType":"SecurityCapabilities","value":""}},"CastShadow":{"type":"bool","value":true},"CollisionGroup":{"type":"string","value":"Default"},"CollisionGroupId":{"type":"int","value":0},"CustomPhysicalProperties":{"type":"nil"},"EnableFluidForces":{"type":"bool","value":true},"FrontSurface":{"type":"Enum","value":{"enumType":"SurfaceType","value":"Smooth"}},"LeftSurface":{"type":"Enum","value":{"enumType":"SurfaceType","value":"Smooth"}},"Locked":{"type":"bool","value":false},"Massless":{"type":"bool","value":false},"Material":{"type":"Enum","value":{"enumType":"Material","value":"Sand"}},"PivotOffset":{"type":"CFrame","value":{"position":[0,0,0],"rotation":[1,0,0,0,1,0,0,0,1]}},"Reflectance":{"type":"float","value":0},"RightSurface":{"type":"Enum","value":{"enumType":"SurfaceType","value":"Smooth"}},"RootPriority":{"type":"int","value":0},"TopSurface":{"type":"Enum","value":{"enumType":"SurfaceType","value":"SmoothNoOutlines"}},"Transparency":{"type":"float","value":0}},"referenceId":"0002e894-2dfa-5334-998d-0000636d6209"},{"className":"Weld","name":"Weld","parentId":"0002e894-2dfa-5334-998d-0000636d6209","path":"ServerStorage.Maps.Amazon.voxels.16916.Weld","properties":{"C0":{"type":"CFrame","value":{"position":[0,-0.5,0],"rotation":[1,0,0,0,0,-1,0,1,0]}},"C1":{"type":"CFrame","value":{"position":[-57.5,0.5,40.5],"rotation":[1,0,0,0,0,-1,0,1,0]}},"Capabilities":{"type":"Enum","value":{"enumType":"SecurityCapabilities","value":""}},"Enabled":{"type":"bool","value":true},"Part0":{"type":"Enum","value":{"enumType":"BasePart","value":"16916"}},"Part1":{"type":"Enum","value":{"enumType":"BasePart","value":"PlayerSpawn"}}},"referenceId":"0002e895-c94d-aad7-bbcb-00004cd36c84"},{"className":"Part","name":"16897","parentId":"00027302-b139-2950-51b5-00005b278fde","path":"ServerStorage.Maps.Amazon.voxels.16897","properties":{"Anchored":{"type":"bool","value":true},"AudioCanCollide":{"type":"bool","value":true},"BackSurface":{"type":"Enum","value":{"enumType":"SurfaceType","value":"Smooth"}},"BottomSurface":{"type":"Enum","value":{"enumType":"SurfaceType","value":"SmoothNoOutlines"}},"CFrame":{"type":"CFrame","value":{"position":[67,1,146],"rotation":[1,0,0,0,1,0,0,0,1]}},"CanCollide":{"type":"bool","value":true},"CanQuery":{"type":"bool","value":true},"CanTouch":{"type":"bool","value":true},"Capabilities":{"type":"Enum","value":{"enumType":"SecurityCapabilities","value":""}},"CastShadow":{"type":"bool","value":true},"CollisionGroup":{"type":"string","value":"Default"},"CollisionGroupId":{"type":"int","value":0},"CustomPhysicalProperties":{"type":"nil"},"EnableFluidForces":{"type":"bool","value":true},"FrontSurface":{"type":"Enum","value":{"enumType":"SurfaceType","value":"Smooth"}},"LeftSurface":{"type":"Enum","value":{"enumType":"SurfaceType","value":"Smooth"}},"Locked":{"type":"bool","value":false},"Massless":{"type":"bool","value":false},"Material":{"type":"Enum","value":{"enumType":"Material","value":"Sand"}},"PivotOffset":{"type":"CFrame","value":{"position":[0,0,0],"rotation":[1,0,0,0,1,0,0,0,1]}},"Reflectance":{"type":"float","value":0},"RightSurface":{"type":"Enum","value":{"enumType":"SurfaceType","value":"Smooth"}},"RootPriority":{"type":"int","value":0},"TopSurface":{"type":"Enum","value":{"enumType":"SurfaceType","value":"SmoothNoOutlines"}},"Transparency":{"type":"float","value":0}},"referenceId":"0002e896-2a8b-9eb2-c1d2-00003774364a"},{"className":"Weld","name":"Weld","parentId":"0002e896-2a8b-9eb2-c1d2-00003774364a","path":"ServerStorage.Maps.Amazon.voxels.16897.Weld","properties":{"C0":{"type":"CFrame","value":{"position":[0,-0.5,0],"rotation":[1,0,0,0,0,-1,0,1,0]}},"C1":{"type":"CFrame","value":{"position":[-57.5,0.5,21.5],"rotation":[1,0,0,0,0,-1,0,1,0]}},"Capabilities":{"type":"Enum","value":{"enumType":"SecurityCapabilities","value":""}},"Enabled":{"type":"bool","value":true},"Part0":{"type":"Enum","value":{"enumType":"BasePart","value":"16897"}},"Part1":{"type":"Enum","value":{"enumType":"BasePart","value":"PlayerSpawn"}}},"referenceId":"0002e897-cb6a-c7a2-f679-000059e2057d"},{"className":"Part","name":"16877","parentId":"00027302-b139-2950-51b5-00005b278fde","path":"ServerStorage.Maps.Amazon.voxels.16877","properties":{"Anchored":{"type":"bool","value":true},"AudioCanCollide":{"type":"bool","value":true},"BackSurface":{"type":"Enum","value":{"enumType":"SurfaceType","value":"Smooth"}},"BottomSurface":{"type":"Enum","value":{"enumType":"SurfaceType","value":"SmoothNoOutlines"}},"CFrame":{"type":"CFrame","value":{"position":[67,1,126],"rotation":[1,0,0,0,1,0,0,0,1]}},"CanCollide":{"type":"bool","value":true},"CanQuery":{"type":"bool","value":true},"CanTouch":{"type":"bool","value":true},"Capabilities":{"type":"Enum","value":{"enumType":"SecurityCapabilities","value":""}},"CastShadow":{"type":"bool","value":true},"CollisionGroup":{"type":"string","value":"Default"},"CollisionGroupId":{"type":"int","value":0},"CustomPhysicalProperties":{"type":"nil"},"EnableFluidForces":{"type":"bool","value":true},"FrontSurface":{"type":"Enum","value":{"enumType":"SurfaceType","value":"Smooth"}},"LeftSurface":{"type":"Enum","value":{"enumType":"SurfaceType","value":"Smooth"}},"Locked":{"type":"bool","value":false},"Massless":{"type":"bool","value":false},"Material":{"type":"Enum","value":{"enumType":"Material","value":"Sand"}},"PivotOffset":{"type":"CFrame","value":{"position":[0,0,0],"rotation":[1,0,0,0,1,0,0,0,1]}},"Reflectance":{"type":"float","value":0},"RightSurface":{"type":"Enum","value":{"enumType":"SurfaceType","value":"Smooth"}},"RootPriority":{"type":"int","value":0},"TopSurface":{"type":"Enum","value":{"enumType":"SurfaceType","value":"SmoothNoOutlines"}},"Transparency":{"type":"float","value":0}},"referenceId":"0002e898-aec1-fa97-53b6-00006954a43b"},{"className":"Weld","name":"Weld","parentId":"0002e898-aec1-fa97-53b6-00006954a43b","path":"ServerStorage.Maps.Amazon.voxels.16877.Weld","properties":{"C0":{"type":"CFrame","value":{"position":[0,-0.5,0],"rotation":[1,0,0,0,0,-1,0,1,0]}},"C1":{"type":"CFrame","value":{"position":[-57.5,0.5,1.5],"rotation":[1,0,0,0,0,-1,0,1,0]}},"Capabilities":{"type":"Enum","value":{"enumType":"SecurityCapabilities","value":""}},"Enabled":{"type":"bool","value":true},"Part0":{"type":"Enum","value":{"enumType":"BasePart","value":"16877"}},"Part1":{"type":"Enum","value":{"enumType":"BasePart","value":"PlayerSpawn"}}},"referenceId":"0002e899-fc56-327e-b3fe-0000230e6c54"},{"className":"Part","name":"16854","parentId":"00027302-b139-2950-51b5-00005b278fde","path":"ServerStorage.Maps.Amazon.voxels.16854","properties":{"Anchored":{"type":"bool","value":true},"AudioCanCollide":{"type":"bool","value":true},"BackSurface":{"type":"Enum","value":{"enumType":"SurfaceType","value":"Smooth"}},"BottomSurface":{"type":"Enum","value":{"enumType":"SurfaceType","value":"SmoothNoOutlines"}},"CFrame":{"type":"CFrame","value":{"position":[67,1,103],"rotation":[1,0,0,0,1,0,0,0,1]}},"CanCollide":{"type":"bool","value":true},"CanQuery":{"type":"bool","value":true},"CanTouch":{"type":"bool","value":true},"Capabilities":{"type":"Enum","value":{"enumType":"SecurityCapabilities","value":""}},"CastShadow":{"type":"bool","value":true},"CollisionGroup":{"type":"string","value":"Default"},"CollisionGroupId":{"type":"int","value":0},"CustomPhysicalProperties":{"type":"nil"},"EnableFluidForces":{"type":"bool","value":true},"FrontSurface":{"type":"Enum","value":{"enumType":"SurfaceType","value":"Smooth"}},"LeftSurface":{"type":"Enum","value":{"enumType":"SurfaceType","value":"Smooth"}},"Locked":{"type":"bool","value":false},"Massless":{"type":"bool","value":false},"Material":{"type":"Enum","value":{"enumType":"Material","value":"Sand"}},"PivotOffset":{"type":"CFrame","value":{"position":[0,0,0],"rotation":[1,0,0,0,1,0,0,0,1]}},"Reflectance":{"type":"float","value":0},"RightSurface":{"type":"Enum","value":{"enumType":"SurfaceType","value":"Smooth"}},"RootPriority":{"type":"int","value":0},"TopSurface":{"type":"Enum","value":{"enumType":"SurfaceType","value":"SmoothNoOutlines"}},"Transparency":{"type":"float","value":0}},"referenceId":"0002e89a-59ba-df15-1849-00005e1269e8"},{"className":"Weld","name":"Weld","parentId":"0002e89a-59ba-df15-1849-00005e1269e8","path":"ServerStorage.Maps.Amazon.voxels.16854.Weld","properties":{"C0":{"type":"CFrame","value":{"position":[0,-0.5,0],"rotation":[1,0,0,0,0,-1,0,1,0]}},"C1":{"type":"CFrame","value":{"position":[-57.5,0.5,-21.5],"rotation":[1,0,0,0,0,-1,0,1,0]}},"Capabilities":{"type":"Enum","value":{"enumType":"SecurityCapabilities","value":""}},"Enabled":{"type":"bool","value":true},"Part0":{"type":"Enum","value":{"enumType":"BasePart","value":"16854"}},"Part1":{"type":"Enum","value":{"enumType":"BasePart","value":"PlayerSpawn"}}},"referenceId":"0002e89b-b28b-8a69-ee76-000053cfb7b6"},{"className":"Part","name":"16898","parentId":"00027302-b139-2950-51b5-00005b278fde","path":"ServerStorage.Maps.Amazon.voxels.16898","properties":{"Anchored":{"type":"bool","value":true},"AudioCanCollide":{"type":"bool","value":true},"BackSurface":{"type":"Enum","value":{"enumType":"SurfaceType","value":"Smooth"}},"BottomSurface":{"type":"Enum","value":{"enumType":"SurfaceType","value":"SmoothNoOutlines"}},"CFrame":{"type":"CFrame","value":{"position":[67,1,147],"rotation":[1,0,0,0,1,0,0,0,1]}},"CanCollide":{"type":"bool","value":true},"CanQuery":{"type":"bool","value":true},"CanTouch":{"type":"bool","value":true},"Capabilities":{"type":"Enum","value":{"enumType":"SecurityCapabilities","value":""}},"CastShadow":{"type":"bool","value":true},"CollisionGroup":{"type":"string","value":"Default"},"CollisionGroupId":{"type":"int","value":0},"CustomPhysicalProperties":{"type":"nil"},"EnableFluidForces":{"type":"bool","value":true},"FrontSurface":{"type":"Enum","value":{"enumType":"SurfaceType","value":"Smooth"}},"LeftSurface":{"type":"Enum","value":{"enumType":"SurfaceType","value":"Smooth"}},"Locked":{"type":"bool","value":false},"Massless":{"type":"bool","value":false},"Material":{"type":"Enum","value":{"enumType":"Material","value":"Sand"}},"PivotOffset":{"type":"CFrame","value":{"position":[0,0,0],"rotation":[1,0,0,0,1,0,0,0,1]}},"Reflectance":{"type":"float","value":0},"RightSurface":{"type":"Enum","value":{"enumType":"SurfaceType","value":"Smooth"}},"RootPriority":{"type":"int","value":0},"TopSurface":{"type":"Enum","value":{"enumType":"SurfaceType","value":"SmoothNoOutlines"}},"Transparency":{"type":"float","value":0}},"referenceId":"0002e89c-7264-f42c-8078-00003b5739b3"},{"className":"Weld","name":"Weld","parentId":"0002e89c-7264-f42c-8078-00003b5739b3","path":"ServerStorage.Maps.Amazon.voxels.16898.Weld","properties":{"C0":{"type":"CFrame","value":{"position":[0,-0.5,0],"rotation":[1,0,0,0,0,-1,0,1,0]}},"C1":{"type":"CFrame","value":{"position":[-57.5,0.5,22.5],"rotation":[1,0,0,0,0,-1,0,1,0]}},"Capabilities":{"type":"Enum","value":{"enumType":"SecurityCapabilities","value":""}},"Enabled":{"type":"bool","value":true},"Part0":{"type":"Enum","value":{"enumType":"BasePart","value":"16898"}},"Part1":{"type":"Enum","value":{"enumType":"BasePart","value":"PlayerSpawn"}}},"referenceId":"0002e89d-ff61-8da2-a9de-00002bf035af"},{"className":"Part","name":"16776","parentId":"00027302-b139-2950-51b5-00005b278fde","path":"ServerStorage.Maps.Amazon.voxels.16776","properties":{"Anchored":{"type":"bool","value":true},"AudioCanCollide":{"type":"bool","value":true},"BackSurface":{"type":"Enum","value":{"enumType":"SurfaceType","value":"Smooth"}},"BottomSurface":{"type":"Enum","value":{"enumType":"SurfaceType","value":"SmoothNoOutlines"}},"CFrame":{"type":"CFrame","value":{"position":[67,1,25],"rotation":[1,0,0,0,1,0,0,0,1]}},"CanCollide":{"type":"bool","value":true},"CanQuery":{"type":"bool","value":true},"CanTouch":{"type":"bool","value":true},"Capabilities":{"type":"Enum","value":{"enumType":"SecurityCapabilities","value":""}},"CastShadow":{"type":"bool","value":true},"CollisionGroup":{"type":"string","value":"Default"},"CollisionGroupId":{"type":"int","value":0},"CustomPhysicalProperties":{"type":"nil"},"EnableFluidForces":{"type":"bool","value":true},"FrontSurface":{"type":"Enum","value":{"enumType":"SurfaceType","value":"Smooth"}},"LeftSurface":{"type":"Enum","value":{"enumType":"SurfaceType","value":"Smooth"}},"Locked":{"type":"bool","value":false},"Massless":{"type":"bool","value":false},"Material":{"type":"Enum","value":{"enumType":"Material","value":"Sand"}},"PivotOffset":{"type":"CFrame","value":{"position":[0,0,0],"rotation":[1,0,0,0,1,0,0,0,1]}},"Reflectance":{"type":"float","value":0},"RightSurface":{"type":"Enum","value":{"enumType":"SurfaceType","value":"Smooth"}},"RootPriority":{"type":"int","value":0},"TopSurface":{"type":"Enum","value":{"enumType":"SurfaceType","value":"SmoothNoOutlines"}},"Transparency":{"type":"float","value":0}},"referenceId":"0002e89e-c1c7-a839-dc6b-000079e130cc"},{"className":"Weld","name":"Weld","parentId":"0002e89e-c1c7-a839-dc6b-000079e130cc","path":"ServerStorage.Maps.Amazon.voxels.16776.Weld","properties":{"C0":{"type":"CFrame","value":{"position":[0,-0.5,0],"rotation":[1,0,0,0,0,-1,0,1,0]}},"C1":{"type":"CFrame","value":{"position":[-57.5,0.5,-99.5],"rotation":[1,0,0,0,0,-1,0,1,0]}},"Capabilities":{"type":"Enum","value":{"enumType":"SecurityCapabilities","value":""}},"Enabled":{"type":"bool","value":true},"Part0":{"type":"Enum","value":{"enumType":"BasePart","value":"16776"}},"Part1":{"type":"Enum","value":{"enumType":"BasePart","value":"PlayerSpawn"}}},"referenceId":"0002e89f-8b6d-27b4-b78b-00006dc01180"},{"className":"Part","name":"16937","parentId":"00027302-b139-2950-51b5-00005b278fde","path":"ServerStorage.Maps.Amazon.voxels.16937","properties":{"Anchored":{"type":"bool","value":true},"AudioCanCollide":{"type":"bool","value":true},"BackSurface":{"type":"Enum","value":{"enumType":"SurfaceType","value":"Smooth"}},"BottomSurface":{"type":"Enum","value":{"enumType":"SurfaceType","value":"SmoothNoOutlines"}},"CFrame":{"type":"CFrame","value":{"position":[67,1,186],"rotation":[1,0,0,0,1,0,0,0,1]}},"CanCollide":{"type":"bool","value":true},"CanQuery":{"type":"bool","value":true},"CanTouch":{"type":"bool","value":true},"Capabilities":{"type":"Enum","value":{"enumType":"SecurityCapabilities","value":""}},"CastShadow":{"type":"bool","value":true},"CollisionGroup":{"type":"string","value":"Default"},"CollisionGroupId":{"type":"int","value":0},"CustomPhysicalProperties":{"type":"nil"},"EnableFluidForces":{"type":"bool","value":true},"FrontSurface":{"type":"Enum","value":{"enumType":"SurfaceType","value":"Smooth"}},"LeftSurface":{"type":"Enum","value":{"enumType":"SurfaceType","value":"Smooth"}},"Locked":{"type":"bool","value":false},"Massless":{"type":"bool","value":false},"Material":{"type":"Enum","value":{"enumType":"Material","value":"Sand"}},"PivotOffset":{"type":"CFrame","value":{"position":[0,0,0],"rotation":[1,0,0,0,1,0,0,0,1]}},"Reflectance":{"type":"float","value":0},"RightSurface":{"type":"Enum","value":{"enumType":"SurfaceType","value":"Smooth"}},"RootPriority":{"type":"int","value":0},"TopSurface":{"type":"Enum","value":{"enumType":"SurfaceType","value":"SmoothNoOutlines"}},"Transparency":{"type":"float","value":0}},"referenceId":"0002e8a0-1373-8555-3eb7-00005f7c54ba"},{"className":"Weld","name":"Weld","parentId":"0002e8a0-1373-8555-3eb7-00005f7c54ba","path":"ServerStorage.Maps.Amazon.voxels.16937.Weld","properties":{"C0":{"type":"CFrame","value":{"position":[0,-0.5,0],"rotation":[1,0,0,0,0,-1,0,1,0]}},"C1":{"type":"CFrame","value":{"position":[-57.5,0.5,61.5],"rotation":[1,0,0,0,0,-1,0,1,0]}},"Capabilities":{"type":"Enum","value":{"enumType":"SecurityCapabilities","value":""}},"Enabled":{"type":"bool","value":true},"Part0":{"type":"Enum","value":{"enumType":"BasePart","value":"16937"}},"Part1":{"type":"Enum","value":{"enumType":"BasePart","value":"PlayerSpawn"}}},"referenceId":"0002e8a1-a605-8004-ed7b-000028a48728"},{"className":"Part","name":"16803","parentId":"00027302-b139-2950-51b5-00005b278fde","path":"ServerStorage.Maps.Amazon.voxels.16803","properties":{"Anchored":{"type":"bool","value":true},"AudioCanCollide":{"type":"bool","value":true},"BackSurface":{"type":"Enum","value":{"enumType":"SurfaceType","value":"Smooth"}},"BottomSurface":{"type":"Enum","value":{"enumType":"SurfaceType","value":"SmoothNoOutlines"}},"CFrame":{"type":"CFrame","value":{"position":[67,1,52],"rotation":[1,0,0,0,1,0,0,0,1]}},"CanCollide":{"type":"bool","value":true},"CanQuery":{"type":"bool","value":true},"CanTouch":{"type":"bool","value":true},"Capabilities":{"type":"Enum","value":{"enumType":"SecurityCapabilities","value":""}},"CastShadow":{"type":"bool","value":true},"CollisionGroup":{"type":"string","value":"Default"},"CollisionGroupId":{"type":"int","value":0},"CustomPhysicalProperties":{"type":"nil"},"EnableFluidForces":{"type":"bool","value":true},"FrontSurface":{"type":"Enum","value":{"enumType":"SurfaceType","value":"Smooth"}},"LeftSurface":{"type":"Enum","value":{"enumType":"SurfaceType","value":"Smooth"}},"Locked":{"type":"bool","value":false},"Massless":{"type":"bool","value":false},"Material":{"type":"Enum","value":{"enumType":"Material","value":"Sand"}},"PivotOffset":{"type":"CFrame","value":{"position":[0,0,0],"rotation":[1,0,0,0,1,0,0,0,1]}},"Reflectance":{"type":"float","value":0},"RightSurface":{"type":"Enum","value":{"enumType":"SurfaceType","value":"Smooth"}},"RootPriority":{"type":"int","value":0},"TopSurface":{"type":"Enum","value":{"enumType":"SurfaceType","value":"SmoothNoOutlines"}},"Transparency":{"type":"float","value":0}},"referenceId":"0002e8a2-3cea-08a6-1141-000058273cd2"},{"className":"Weld","name":"Weld","parentId":"0002e8a2-3cea-08a6-1141-000058273cd2","path":"ServerStorage.Maps.Amazon.voxels.16803.Weld","properties":{"C0":{"type":"CFrame","value":{"position":[0,-0.5,0],"rotation":[1,0,0,0,0,-1,0,1,0]}},"C1":{"type":"CFrame","value":{"position":[-57.5,0.5,-72.5],"rotation":[1,0,0,0,0,-1,0,1,0]}},"Capabilities":{"type":"Enum","value":{"enumType":"SecurityCapabilities","value":""}},"Enabled":{"type":"bool","value":true},"Part0":{"type":"Enum","value":{"enumType":"BasePart","value":"16803"}},"Part1":{"type":"Enum","value":{"enumType":"BasePart","value":"PlayerSpawn"}}},"referenceId":"0002e8a3-45de-779e-01ff-00002f61bbf9"},{"className":"Part","name":"16959","parentId":"00027302-b139-2950-51b5-00005b278fde","path":"ServerStorage.Maps.Amazon.voxels.16959","properties":{"Anchored":{"type":"bool","value":true},"AudioCanCollide":{"type":"bool","value":true},"BackSurface":{"type":"Enum","value":{"enumType":"SurfaceType","value":"Smooth"}},"BottomSurface":{"type":"Enum","value":{"enumType":"SurfaceType","value":"SmoothNoOutlines"}},"CFrame":{"type":"CFrame","value":{"position":[67,1,208],"rotation":[1,0,0,0,1,0,0,0,1]}},"CanCollide":{"type":"bool","value":true},"CanQuery":{"type":"bool","value":true},"CanTouch":{"type":"bool","value":true},"Capabilities":{"type":"Enum","value":{"enumType":"SecurityCapabilities","value":""}},"CastShadow":{"type":"bool","value":true},"CollisionGroup":{"type":"string","value":"Default"},"CollisionGroupId":{"type":"int","value":0},"CustomPhysicalProperties":{"type":"nil"},"EnableFluidForces":{"type":"bool","value":true},"FrontSurface":{"type":"Enum","value":{"enumType":"SurfaceType","value":"Smooth"}},"LeftSurface":{"type":"Enum","value":{"enumType":"SurfaceType","value":"Smooth"}},"Locked":{"type":"bool","value":false},"Massless":{"type":"bool","value":false},"Material":{"type":"Enum","value":{"enumType":"Material","value":"Sand"}},"PivotOffset":{"type":"CFrame","value":{"position":[0,0,0],"rotation":[1,0,0,0,1,0,0,0,1]}},"Reflectance":{"type":"float","value":0},"RightSurface":{"type":"Enum","value":{"enumType":"SurfaceType","value":"Smooth"}},"RootPriority":{"type":"int","value":0},"TopSurface":{"type":"Enum","value":{"enumType":"SurfaceType","value":"SmoothNoOutlines"}},"Transparency":{"type":"float","value":0}},"referenceId":"0002e8a4-d47c-0161-ea44-000033ed54c2"},{"className":"Weld","name":"Weld","parentId":"0002e8a4-d47c-0161-ea44-000033ed54c2","path":"ServerStorage.Maps.Amazon.voxels.16959.Weld","properties":{"C0":{"type":"CFrame","value":{"position":[0,-0.5,0],"rotation":[1,0,0,0,0,-1,0,1,0]}},"C1":{"type":"CFrame","value":{"position":[-57.5,0.5,83.5],"rotation":[1,0,0,0,0,-1,0,1,0]}},"Capabilities":{"type":"Enum","value":{"enumType":"SecurityCapabilities","value":""}},"Enabled":{"type":"bool","value":true},"Part0":{"type":"Enum","value":{"enumType":"BasePart","value":"16959"}},"Part1":{"type":"Enum","value":{"enumType":"BasePart","value":"PlayerSpawn"}}},"referenceId":"0002e8a5-4189-9c3f-3334-000070de8a3c"},{"className":"Part","name":"16887","parentId":"00027302-b139-2950-51b5-00005b278fde","path":"ServerStorage.Maps.Amazon.voxels.16887","properties":{"Anchored":{"type":"bool","value":true},"AudioCanCollide":{"type":"bool","value":true},"BackSurface":{"type":"Enum","value":{"enumType":"SurfaceType","value":"Smooth"}},"BottomSurface":{"type":"Enum","value":{"enumType":"SurfaceType","value":"SmoothNoOutlines"}},"CFrame":{"type":"CFrame","value":{"position":[67,1,136],"rotation":[1,0,0,0,1,0,0,0,1]}},"CanCollide":{"type":"bool","value":true},"CanQuery":{"type":"bool","value":true},"CanTouch":{"type":"bool","value":true},"Capabilities":{"type":"Enum","value":{"enumType":"SecurityCapabilities","value":""}},"CastShadow":{"type":"bool","value":true},"CollisionGroup":{"type":"string","value":"Default"},"CollisionGroupId":{"type":"int","value":0},"CustomPhysicalProperties":{"type":"nil"},"EnableFluidForces":{"type":"bool","value":true},"FrontSurface":{"type":"Enum","value":{"enumType":"SurfaceType","value":"Smooth"}},"LeftSurface":{"type":"Enum","value":{"enumType":"SurfaceType","value":"Smooth"}},"Locked":{"type":"bool","value":false},"Massless":{"type":"bool","value":false},"Material":{"type":"Enum","value":{"enumType":"Material","value":"Sand"}},"PivotOffset":{"type":"CFrame","value":{"position":[0,0,0],"rotation":[1,0,0,0,1,0,0,0,1]}},"Reflectance":{"type":"float","value":0},"RightSurface":{"type":"Enum","value":{"enumType":"SurfaceType","value":"Smooth"}},"RootPriority":{"type":"int","value":0},"TopSurface":{"type":"Enum","value":{"enumType":"SurfaceType","value":"SmoothNoOutlines"}},"Transparency":{"type":"float","value":0}},"referenceId":"0002e8a6-fa1d-36ce-bcf5-00000a4f8795"},{"className":"Weld","name":"Weld","parentId":"0002e8a6-fa1d-36ce-bcf5-00000a4f8795","path":"ServerStorage.Maps.Amazon.voxels.16887.Weld","properties":{"C0":{"type":"CFrame","value":{"position":[0,-0.5,0],"rotation":[1,0,0,0,0,-1,0,1,0]}},"C1":{"type":"CFrame","value":{"position":[-57.5,0.5,11.5],"rotation":[1,0,0,0,0,-1,0,1,0]}},"Capabilities":{"type":"Enum","value":{"enumType":"SecurityCapabilities","value":""}},"Enabled":{"type":"bool","value":true},"Part0":{"type":"Enum","value":{"enumType":"BasePart","value":"16887"}},"Part1":{"type":"Enum","value":{"enumType":"BasePart","value":"PlayerSpawn"}}},"referenceId":"0002e8a7-5997-6a62-a5ef-000055271cf5"},{"className":"Part","name":"16781","parentId":"00027302-b139-2950-51b5-00005b278fde","path":"ServerStorage.Maps.Amazon.voxels.16781","properties":{"Anchored":{"type":"bool","value":true},"AudioCanCollide":{"type":"bool","value":true},"BackSurface":{"type":"Enum","value":{"enumType":"SurfaceType","value":"Smooth"}},"BottomSurface":{"type":"Enum","value":{"enumType":"SurfaceType","value":"SmoothNoOutlines"}},"CFrame":{"type":"CFrame","value":{"position":[67,1,30],"rotation":[1,0,0,0,1,0,0,0,1]}},"CanCollide":{"type":"bool","value":true},"CanQuery":{"type":"bool","value":true},"CanTouch":{"type":"bool","value":true},"Capabilities":{"type":"Enum","value":{"enumType":"SecurityCapabilities","value":""}},"CastShadow":{"type":"bool","value":true},"CollisionGroup":{"type":"string","value":"Default"},"CollisionGroupId":{"type":"int","value":0},"CustomPhysicalProperties":{"type":"nil"},"EnableFluidForces":{"type":"bool","value":true},"FrontSurface":{"type":"Enum","value":{"enumType":"SurfaceType","value":"Smooth"}},"LeftSurface":{"type":"Enum","value":{"enumType":"SurfaceType","value":"Smooth"}},"Locked":{"type":"bool","value":false},"Massless":{"type":"bool","value":false},"Material":{"type":"Enum","value":{"enumType":"Material","value":"Sand"}},"PivotOffset":{"type":"CFrame","value":{"position":[0,0,0],"rotation":[1,0,0,0,1,0,0,0,1]}},"Reflectance":{"type":"float","value":0},"RightSurface":{"type":"Enum","value":{"enumType":"SurfaceType","value":"Smooth"}},"RootPriority":{"type":"int","value":0},"TopSurface":{"type":"Enum","value":{"enumType":"SurfaceType","value":"SmoothNoOutlines"}},"Transparency":{"type":"float","value":0}},"referenceId":"0002e8a8-b851-5542-b423-00006de42fbd"},{"className":"Weld","name":"Weld","parentId":"0002e8a8-b851-5542-b423-00006de42fbd","path":"ServerStorage.Maps.Amazon.voxels.16781.Weld","properties":{"C0":{"type":"CFrame","value":{"position":[0,-0.5,0],"rotation":[1,0,0,0,0,-1,0,1,0]}},"C1":{"type":"CFrame","value":{"position":[-57.5,0.5,-94.5],"rotation":[1,0,0,0,0,-1,0,1,0]}},"Capabilities":{"type":"Enum","value":{"enumType":"SecurityCapabilities","value":""}},"Enabled":{"type":"bool","value":true},"Part0":{"type":"Enum","value":{"enumType":"BasePart","value":"16781"}},"Part1":{"type":"Enum","value":{"enumType":"BasePart","value":"PlayerSpawn"}}},"referenceId":"0002e8a9-0851-afd2-6fad-000002a61ccb"},{"className":"Part","name":"16900","parentId":"00027302-b139-2950-51b5-00005b278fde","path":"ServerStorage.Maps.Amazon.voxels.16900","properties":{"Anchored":{"type":"bool","value":true},"AudioCanCollide":{"type":"bool","value":true},"BackSurface":{"type":"Enum","value":{"enumType":"SurfaceType","value":"Smooth"}},"BottomSurface":{"type":"Enum","value":{"enumType":"SurfaceType","value":"SmoothNoOutlines"}},"CFrame":{"type":"CFrame","value":{"position":[67,1,149],"rotation":[1,0,0,0,1,0,0,0,1]}},"CanCollide":{"type":"bool","value":true},"CanQuery":{"type":"bool","value":true},"CanTouch":{"type":"bool","value":true},"Capabilities":{"type":"Enum","value":{"enumType":"SecurityCapabilities","value":""}},"CastShadow":{"type":"bool","value":true},"CollisionGroup":{"type":"string","value":"Default"},"CollisionGroupId":{"type":"int","value":0},"CustomPhysicalProperties":{"type":"nil"},"EnableFluidForces":{"type":"bool","value":true},"FrontSurface":{"type":"Enum","value":{"enumType":"SurfaceType","value":"Smooth"}},"LeftSurface":{"type":"Enum","value":{"enumType":"SurfaceType","value":"Smooth"}},"Locked":{"type":"bool","value":false},"Massless":{"type":"bool","value":false},"Material":{"type":"Enum","value":{"enumType":"Material","value":"Sand"}},"PivotOffset":{"type":"CFrame","value":{"position":[0,0,0],"rotation":[1,0,0,0,1,0,0,0,1]}},"Reflectance":{"type":"float","value":0},"RightSurface":{"type":"Enum","value":{"enumType":"SurfaceType","value":"Smooth"}},"RootPriority":{"type":"int","value":0},"TopSurface":{"type":"Enum","value":{"enumType":"SurfaceType","value":"SmoothNoOutlines"}},"Transparency":{"type":"float","value":0}},"referenceId":"0002e8aa-51d9-1088-622c-000025be94ee"},{"className":"Weld","name":"Weld","parentId":"0002e8aa-51d9-1088-622c-000025be94ee","path":"ServerStorage.Maps.Amazon.voxels.16900.Weld","properties":{"C0":{"type":"CFrame","value":{"position":[0,-0.5,0],"rotation":[1,0,0,0,0,-1,0,1,0]}},"C1":{"type":"CFrame","value":{"position":[-57.5,0.5,24.5],"rotation":[1,0,0,0,0,-1,0,1,0]}},"Capabilities":{"type":"Enum","value":{"enumType":"SecurityCapabilities","value":""}},"Enabled":{"type":"bool","value":true},"Part0":{"type":"Enum","value":{"enumType":"BasePart","value":"16900"}},"Part1":{"type":"Enum","value":{"enumType":"BasePart","value":"PlayerSpawn"}}},"referenceId":"0002e8ab-14ec-1c46-2ea3-00003e09c8a3"},{"className":"Part","name":"16860","parentId":"00027302-b139-2950-51b5-00005b278fde","path":"ServerStorage.Maps.Amazon.voxels.16860","properties":{"Anchored":{"type":"bool","value":true},"AudioCanCollide":{"type":"bool","value":true},"BackSurface":{"type":"Enum","value":{"enumType":"SurfaceType","value":"Smooth"}},"BottomSurface":{"type":"Enum","value":{"enumType":"SurfaceType","value":"SmoothNoOutlines"}},"CFrame":{"type":"CFrame","value":{"position":[67,1,109],"rotation":[1,0,0,0,1,0,0,0,1]}},"CanCollide":{"type":"bool","value":true},"CanQuery":{"type":"bool","value":true},"CanTouch":{"type":"bool","value":true},"Capabilities":{"type":"Enum","value":{"enumType":"SecurityCapabilities","value":""}},"CastShadow":{"type":"bool","value":true},"CollisionGroup":{"type":"string","value":"Default"},"CollisionGroupId":{"type":"int","value":0},"CustomPhysicalProperties":{"type":"nil"},"EnableFluidForces":{"type":"bool","value":true},"FrontSurface":{"type":"Enum","value":{"enumType":"SurfaceType","value":"Smooth"}},"LeftSurface":{"type":"Enum","value":{"enumType":"SurfaceType","value":"Smooth"}},"Locked":{"type":"bool","value":false},"Massless":{"type":"bool","value":false},"Material":{"type":"Enum","value":{"enumType":"Material","value":"Sand"}},"PivotOffset":{"type":"CFrame","value":{"position":[0,0,0],"rotation":[1,0,0,0,1,0,0,0,1]}},"Reflectance":{"type":"float","value":0},"RightSurface":{"type":"Enum","value":{"enumType":"SurfaceType","value":"Smooth"}},"RootPriority":{"type":"int","value":0},"TopSurface":{"type":"Enum","value":{"enumType":"SurfaceType","value":"SmoothNoOutlines"}},"Transparency":{"type":"float","value":0}},"referenceId":"0002e8ac-3caf-4b6f-db9c-0000390f6094"},{"className":"Weld","name":"Weld","parentId":"0002e8ac-3caf-4b6f-db9c-0000390f6094","path":"ServerStorage.Maps.Amazon.voxels.16860.Weld","properties":{"C0":{"type":"CFrame","value":{"position":[0,-0.5,0],"rotation":[1,0,0,0,0,-1,0,1,0]}},"C1":{"type":"CFrame","value":{"position":[-57.5,0.5,-15.5],"rotation":[1,0,0,0,0,-1,0,1,0]}},"Capabilities":{"type":"Enum","value":{"enumType":"SecurityCapabilities","value":""}},"Enabled":{"type":"bool","value":true},"Part0":{"type":"Enum","value":{"enumType":"BasePart","value":"16860"}},"Part1":{"type":"Enum","value":{"enumType":"BasePart","value":"PlayerSpawn"}}},"referenceId":"0002e8ad-e325-923a-891d-000013f33fbd"},{"className":"Part","name":"16760","parentId":"00027302-b139-2950-51b5-00005b278fde","path":"ServerStorage.Maps.Amazon.voxels.16760","properties":{"Anchored":{"type":"bool","value":true},"AudioCanCollide":{"type":"bool","value":true},"BackSurface":{"type":"Enum","value":{"enumType":"SurfaceType","value":"Smooth"}},"BottomSurface":{"type":"Enum","value":{"enumType":"SurfaceType","value":"SmoothNoOutlines"}},"CFrame":{"type":"CFrame","value":{"position":[67,0.5,9],"rotation":[1,0,0,0,1,0,0,0,1]}},"CanCollide":{"type":"bool","value":true},"CanQuery":{"type":"bool","value":true},"CanTouch":{"type":"bool","value":true},"Capabilities":{"type":"Enum","value":{"enumType":"SecurityCapabilities","value":""}},"CastShadow":{"type":"bool","value":false},"CollisionGroup":{"type":"string","value":"Default"},"CollisionGroupId":{"type":"int","value":0},"CustomPhysicalProperties":{"type":"nil"},"EnableFluidForces":{"type":"bool","value":true},"FrontSurface":{"type":"Enum","value":{"enumType":"SurfaceType","value":"Smooth"}},"LeftSurface":{"type":"Enum","value":{"enumType":"SurfaceType","value":"Smooth"}},"Locked":{"type":"bool","value":false},"Massless":{"type":"bool","value":false},"Material":{"type":"Enum","value":{"enumType":"Material","value":"Plastic"}},"PivotOffset":{"type":"CFrame","value":{"position":[0,0,0],"rotation":[1,0,0,0,1,0,0,0,1]}},"Reflectance":{"type":"float","value":0},"RightSurface":{"type":"Enum","value":{"enumType":"SurfaceType","value":"Smooth"}},"RootPriority":{"type":"int","value":0},"TopSurface":{"type":"Enum","value":{"enumType":"SurfaceType","value":"SmoothNoOutlines"}},"Transparency":{"type":"float","value":0}},"referenceId":"0002e8ae-a84b-3ca6-2924-00007de2e159"},{"className":"Part","name":"16771","parentId":"00027302-b139-2950-51b5-00005b278fde","path":"ServerStorage.Maps.Amazon.voxels.16771","properties":{"Anchored":{"type":"bool","value":true},"AudioCanCollide":{"type":"bool","value":true},"BackSurface":{"type":"Enum","value":{"enumType":"SurfaceType","value":"Smooth"}},"BottomSurface":{"type":"Enum","value":{"enumType":"SurfaceType","value":"SmoothNoOutlines"}},"CFrame":{"type":"CFrame","value":{"position":[67,1,20],"rotation":[1,0,0,0,1,0,0,0,1]}},"CanCollide":{"type":"bool","value":true},"CanQuery":{"type":"bool","value":true},"CanTouch":{"type":"bool","value":true},"Capabilities":{"type":"Enum","value":{"enumType":"SecurityCapabilities","value":""}},"CastShadow":{"type":"bool","value":true},"CollisionGroup":{"type":"string","value":"Default"},"CollisionGroupId":{"type":"int","value":0},"CustomPhysicalProperties":{"type":"nil"},"EnableFluidForces":{"type":"bool","value":true},"FrontSurface":{"type":"Enum","value":{"enumType":"SurfaceType","value":"Smooth"}},"LeftSurface":{"type":"Enum","value":{"enumType":"SurfaceType","value":"Smooth"}},"Locked":{"type":"bool","value":false},"Massless":{"type":"bool","value":false},"Material":{"type":"Enum","value":{"enumType":"Material","value":"Sand"}},"PivotOffset":{"type":"CFrame","value":{"position":[0,0,0],"rotation":[1,0,0,0,1,0,0,0,1]}},"Reflectance":{"type":"float","value":0},"RightSurface":{"type":"Enum","value":{"enumType":"SurfaceType","value":"Smooth"}},"RootPriority":{"type":"int","value":0},"TopSurface":{"type":"Enum","value":{"enumType":"SurfaceType","value":"SmoothNoOutlines"}},"Transparency":{"type":"float","value":0}},"referenceId":"0002e8af-11f6-2d6f-1d78-00005ed605dd"},{"className":"Weld","name":"Weld","parentId":"0002e8af-11f6-2d6f-1d78-00005ed605dd","path":"ServerStorage.Maps.Amazon.voxels.16771.Weld","properties":{"C0":{"type":"CFrame","value":{"position":[0,-0.5,0],"rotation":[1,0,0,0,0,-1,0,1,0]}},"C1":{"type":"CFrame","value":{"position":[-57.5,0.5,-104.5],"rotation":[1,0,0,0,0,-1,0,1,0]}},"Capabilities":{"type":"Enum","value":{"enumType":"SecurityCapabilities","value":""}},"Enabled":{"type":"bool","value":true},"Part0":{"type":"Enum","value":{"enumType":"BasePart","value":"16771"}},"Part1":{"type":"Enum","value":{"enumType":"BasePart","value":"PlayerSpawn"}}},"referenceId":"0002e8b0-0320-460e-7a2b-000065d3d3a4"},{"className":"Part","name":"16966","parentId":"00027302-b139-2950-51b5-00005b278fde","path":"ServerStorage.Maps.Amazon.voxels.16966","properties":{"Anchored":{"type":"bool","value":true},"AudioCanCollide":{"type":"bool","value":true},"BackSurface":{"type":"Enum","value":{"enumType":"SurfaceType","value":"Smooth"}},"BottomSurface":{"type":"Enum","value":{"enumType":"SurfaceType","value":"SmoothNoOutlines"}},"CFrame":{"type":"CFrame","value":{"position":[67,0.5,215],"rotation":[1,0,0,0,1,0,0,0,1]}},"CanCollide":{"type":"bool","value":true},"CanQuery":{"type":"bool","value":true},"CanTouch":{"type":"bool","value":true},"Capabilities":{"type":"Enum","value":{"enumType":"SecurityCapabilities","value":""}},"CastShadow":{"type":"bool","value":false},"CollisionGroup":{"type":"string","value":"Default"},"CollisionGroupId":{"type":"int","value":0},"CustomPhysicalProperties":{"type":"nil"},"EnableFluidForces":{"type":"bool","value":true},"FrontSurface":{"type":"Enum","value":{"enumType":"SurfaceType","value":"Smooth"}},"LeftSurface":{"type":"Enum","value":{"enumType":"SurfaceType","value":"Smooth"}},"Locked":{"type":"bool","value":false},"Massless":{"type":"bool","value":false},"Material":{"type":"Enum","value":{"enumType":"Material","value":"Plastic"}},"PivotOffset":{"type":"CFrame","value":{"position":[0,0,0],"rotation":[1,0,0,0,1,0,0,0,1]}},"Reflectance":{"type":"float","value":0},"RightSurface":{"type":"Enum","value":{"enumType":"SurfaceType","value":"Smooth"}},"RootPriority":{"type":"int","value":0},"TopSurface":{"type":"Enum","value":{"enumType":"SurfaceType","value":"SmoothNoOutlines"}},"Transparency":{"type":"float","value":0}},"referenceId":"0002e8b1-7ba8-48eb-81e2-000074f374d2"},{"className":"Part","name":"16838","parentId":"00027302-b139-2950-51b5-00005b278fde","path":"ServerStorage.Maps.Amazon.voxels.16838","properties":{"Anchored":{"type":"bool","value":true},"AudioCanCollide":{"type":"bool","value":true},"BackSurface":{"type":"Enum","value":{"enumType":"SurfaceType","value":"Smooth"}},"BottomSurface":{"type":"Enum","value":{"enumType":"SurfaceType","value":"SmoothNoOutlines"}},"CFrame":{"type":"CFrame","value":{"position":[67,0.5,87],"rotation":[1,0,0,0,1,0,0,0,1]}},"CanCollide":{"type":"bool","value":true},"CanQuery":{"type":"bool","value":true},"CanTouch":{"type":"bool","value":true},"Capabilities":{"type":"Enum","value":{"enumType":"SecurityCapabilities","value":""}},"CastShadow":{"type":"bool","value":false},"CollisionGroup":{"type":"string","value":"Default"},"CollisionGroupId":{"type":"int","value":0},"CustomPhysicalProperties":{"type":"nil"},"EnableFluidForces":{"type":"bool","value":true},"FrontSurface":{"type":"Enum","value":{"enumType":"SurfaceType","value":"Smooth"}},"LeftSurface":{"type":"Enum","value":{"enumType":"SurfaceType","value":"Smooth"}},"Locked":{"type":"bool","value":false},"Massless":{"type":"bool","value":false},"Material":{"type":"Enum","value":{"enumType":"Material","value":"Plastic"}},"PivotOffset":{"type":"CFrame","value":{"position":[0,0,0],"rotation":[1,0,0,0,1,0,0,0,1]}},"Reflectance":{"type":"float","value":0},"RightSurface":{"type":"Enum","value":{"enumType":"SurfaceType","value":"Smooth"}},"RootPriority":{"type":"int","value":0},"TopSurface":{"type":"Enum","value":{"enumType":"SurfaceType","value":"SmoothNoOutlines"}},"Transparency":{"type":"float","value":0}},"referenceId":"0002e8b2-3694-ada7-532b-0000729ca768"},{"className":"Part","name":"16840","parentId":"00027302-b139-2950-51b5-00005b278fde","path":"ServerStorage.Maps.Amazon.voxels.16840","properties":{"Anchored":{"type":"bool","value":true},"AudioCanCollide":{"type":"bool","value":true},"BackSurface":{"type":"Enum","value":{"enumType":"SurfaceType","value":"Smooth"}},"BottomSurface":{"type":"Enum","value":{"enumType":"SurfaceType","value":"SmoothNoOutlines"}},"CFrame":{"type":"CFrame","value":{"position":[67,0.5,89],"rotation":[1,0,0,0,1,0,0,0,1]}},"CanCollide":{"type":"bool","value":true},"CanQuery":{"type":"bool","value":true},"CanTouch":{"type":"bool","value":true},"Capabilities":{"type":"Enum","value":{"enumType":"SecurityCapabilities","value":""}},"CastShadow":{"type":"bool","value":false},"CollisionGroup":{"type":"string","value":"Default"},"CollisionGroupId":{"type":"int","value":0},"CustomPhysicalProperties":{"type":"nil"},"EnableFluidForces":{"type":"bool","value":true},"FrontSurface":{"type":"Enum","value":{"enumType":"SurfaceType","value":"Smooth"}},"LeftSurface":{"type":"Enum","value":{"enumType":"SurfaceType","value":"Smooth"}},"Locked":{"type":"bool","value":false},"Massless":{"type":"bool","value":false},"Material":{"type":"Enum","value":{"enumType":"Material","value":"Plastic"}},"PivotOffset":{"type":"CFrame","value":{"position":[0,0,0],"rotation":[1,0,0,0,1,0,0,0,1]}},"Reflectance":{"type":"float","value":0},"RightSurface":{"type":"Enum","value":{"enumType":"SurfaceType","value":"Smooth"}},"RootPriority":{"type":"int","value":0},"TopSurface":{"type":"Enum","value":{"enumType":"SurfaceType","value":"SmoothNoOutlines"}},"Transparency":{"type":"float","value":0}},"referenceId":"0002e8b3-c51b-c6e1-96b2-00000e017c3f"},{"className":"Part","name":"16892","parentId":"00027302-b139-2950-51b5-00005b278fde","path":"ServerStorage.Maps.Amazon.voxels.16892","properties":{"Anchored":{"type":"bool","value":true},"AudioCanCollide":{"type":"bool","value":true},"BackSurface":{"type":"Enum","value":{"enumType":"SurfaceType","value":"Smooth"}},"BottomSurface":{"type":"Enum","value":{"enumType":"SurfaceType","value":"SmoothNoOutlines"}},"CFrame":{"type":"CFrame","value":{"position":[67,0.5,141],"rotation":[1,0,0,0,1,0,0,0,1]}},"CanCollide":{"type":"bool","value":true},"CanQuery":{"type":"bool","value":true},"CanTouch":{"type":"bool","value":true},"Capabilities":{"type":"Enum","value":{"enumType":"SecurityCapabilities","value":""}},"CastShadow":{"type":"bool","value":false},"CollisionGroup":{"type":"string","value":"Default"},"CollisionGroupId":{"type":"int","value":0},"CustomPhysicalProperties":{"type":"nil"},"EnableFluidForces":{"type":"bool","value":true},"FrontSurface":{"type":"Enum","value":{"enumType":"SurfaceType","value":"Smooth"}},"LeftSurface":{"type":"Enum","value":{"enumType":"SurfaceType","value":"Smooth"}},"Locked":{"type":"bool","value":false},"Massless":{"type":"bool","value":false},"Material":{"type":"Enum","value":{"enumType":"Material","value":"Plastic"}},"PivotOffset":{"type":"CFrame","value":{"position":[0,0,0],"rotation":[1,0,0,0,1,0,0,0,1]}},"Reflectance":{"type":"float","value":0},"RightSurface":{"type":"Enum","value":{"enumType":"SurfaceType","value":"Smooth"}},"RootPriority":{"type":"int","value":0},"TopSurface":{"type":"Enum","value":{"enumType":"SurfaceType","value":"SmoothNoOutlines"}},"Transparency":{"type":"float","value":0}},"referenceId":"0002e8b4-616f-2b00-cf08-00002f962002"},{"className":"Part","name":"16894","parentId":"00027302-b139-2950-51b5-00005b278fde","path":"ServerStorage.Maps.Amazon.voxels.16894","properties":{"Anchored":{"type":"bool","value":true},"AudioCanCollide":{"type":"bool","value":true},"BackSurface":{"type":"Enum","value":{"enumType":"SurfaceType","value":"Smooth"}},"BottomSurface":{"type":"Enum","value":{"enumType":"SurfaceType","value":"SmoothNoOutlines"}},"CFrame":{"type":"CFrame","value":{"position":[67,1,143],"rotation":[1,0,0,0,1,0,0,0,1]}},"CanCollide":{"type":"bool","value":true},"CanQuery":{"type":"bool","value":true},"CanTouch":{"type":"bool","value":true},"Capabilities":{"type":"Enum","value":{"enumType":"SecurityCapabilities","value":""}},"CastShadow":{"type":"bool","value":true},"CollisionGroup":{"type":"string","value":"Default"},"CollisionGroupId":{"type":"int","value":0},"CustomPhysicalProperties":{"type":"nil"},"EnableFluidForces":{"type":"bool","value":true},"FrontSurface":{"type":"Enum","value":{"enumType":"SurfaceType","value":"Smooth"}},"LeftSurface":{"type":"Enum","value":{"enumType":"SurfaceType","value":"Smooth"}},"Locked":{"type":"bool","value":false},"Massless":{"type":"bool","value":false},"Material":{"type":"Enum","value":{"enumType":"Material","value":"Sand"}},"PivotOffset":{"type":"CFrame","value":{"position":[0,0,0],"rotation":[1,0,0,0,1,0,0,0,1]}},"Reflectance":{"type":"float","value":0},"RightSurface":{"type":"Enum","value":{"enumType":"SurfaceType","value":"Smooth"}},"RootPriority":{"type":"int","value":0},"TopSurface":{"type":"Enum","value":{"enumType":"SurfaceType","value":"SmoothNoOutlines"}},"Transparency":{"type":"float","value":0}},"referenceId":"0002e8b5-66f5-a07f-af6c-000031039ca2"},{"className":"Weld","name":"Weld","parentId":"0002e8b5-66f5-a07f-af6c-000031039ca2","path":"ServerStorage.Maps.Amazon.voxels.16894.Weld","properties":{"C0":{"type":"CFrame","value":{"position":[0,-0.5,0],"rotation":[1,0,0,0,0,-1,0,1,0]}},"C1":{"type":"CFrame","value":{"position":[-57.5,0.5,18.5],"rotation":[1,0,0,0,0,-1,0,1,0]}},"Capabilities":{"type":"Enum","value":{"enumType":"SecurityCapabilities","value":""}},"Enabled":{"type":"bool","value":true},"Part0":{"type":"Enum","value":{"enumType":"BasePart","value":"16894"}},"Part1":{"type":"Enum","value":{"enumType":"BasePart","value":"PlayerSpawn"}}},"referenceId":"0002e8b6-64f2-03d6-f7e3-00006969f7a6"},{"className":"Part","name":"16984","parentId":"00027302-b139-2950-51b5-00005b278fde","path":"ServerStorage.Maps.Amazon.voxels.16984","properties":{"Anchored":{"type":"bool","value":true},"AudioCanCollide":{"type":"bool","value":true},"BackSurface":{"type":"Enum","value":{"enumType":"SurfaceType","value":"Smooth"}},"BottomSurface":{"type":"Enum","value":{"enumType":"SurfaceType","value":"SmoothNoOutlines"}},"CFrame":{"type":"CFrame","value":{"position":[67,1,233],"rotation":[1,0,0,0,1,0,0,0,1]}},"CanCollide":{"type":"bool","value":true},"CanQuery":{"type":"bool","value":true},"CanTouch":{"type":"bool","value":true},"Capabilities":{"type":"Enum","value":{"enumType":"SecurityCapabilities","value":""}},"CastShadow":{"type":"bool","value":true},"CollisionGroup":{"type":"string","value":"Default"},"CollisionGroupId":{"type":"int","value":0},"CustomPhysicalProperties":{"type":"nil"},"EnableFluidForces":{"type":"bool","value":true},"FrontSurface":{"type":"Enum","value":{"enumType":"SurfaceType","value":"Smooth"}},"LeftSurface":{"type":"Enum","value":{"enumType":"SurfaceType","value":"Smooth"}},"Locked":{"type":"bool","value":false},"Massless":{"type":"bool","value":false},"Material":{"type":"Enum","value":{"enumType":"Material","value":"Sand"}},"PivotOffset":{"type":"CFrame","value":{"position":[0,0,0],"rotation":[1,0,0,0,1,0,0,0,1]}},"Reflectance":{"type":"float","value":0},"RightSurface":{"type":"Enum","value":{"enumType":"SurfaceType","value":"Smooth"}},"RootPriority":{"type":"int","value":0},"TopSurface":{"type":"Enum","value":{"enumType":"SurfaceType","value":"SmoothNoOutlines"}},"Transparency":{"type":"float","value":0}},"referenceId":"0002e8b7-3249-8b3f-64bd-0000011ec172"},{"className":"Weld","name":"Weld","parentId":"0002e8b7-3249-8b3f-64bd-0000011ec172","path":"ServerStorage.Maps.Amazon.voxels.16984.Weld","properties":{"C0":{"type":"CFrame","value":{"position":[0,-0.5,0],"rotation":[1,0,0,0,0,-1,0,1,0]}},"C1":{"type":"CFrame","value":{"position":[-57.5,0.5,108.5],"rotation":[1,0,0,0,0,-1,0,1,0]}},"Capabilities":{"type":"Enum","value":{"enumType":"SecurityCapabilities","value":""}},"Enabled":{"type":"bool","value":true},"Part0":{"type":"Enum","value":{"enumType":"BasePart","value":"16984"}},"Part1":{"type":"Enum","value":{"enumType":"BasePart","value":"PlayerSpawn"}}},"referenceId":"0002e8b8-a5cb-6037-dada-000068a51baa"},{"className":"Part","name":"16786","parentId":"00027302-b139-2950-51b5-00005b278fde","path":"ServerStorage.Maps.Amazon.voxels.16786","properties":{"Anchored":{"type":"bool","value":true},"AudioCanCollide":{"type":"bool","value":true},"BackSurface":{"type":"Enum","value":{"enumType":"SurfaceType","value":"Smooth"}},"BottomSurface":{"type":"Enum","value":{"enumType":"SurfaceType","value":"SmoothNoOutlines"}},"CFrame":{"type":"CFrame","value":{"position":[67,1,35],"rotation":[1,0,0,0,1,0,0,0,1]}},"CanCollide":{"type":"bool","value":true},"CanQuery":{"type":"bool","value":true},"CanTouch":{"type":"bool","value":true},"Capabilities":{"type":"Enum","value":{"enumType":"SecurityCapabilities","value":""}},"CastShadow":{"type":"bool","value":true},"CollisionGroup":{"type":"string","value":"Default"},"CollisionGroupId":{"type":"int","value":0},"CustomPhysicalProperties":{"type":"nil"},"EnableFluidForces":{"type":"bool","value":true},"FrontSurface":{"type":"Enum","value":{"enumType":"SurfaceType","value":"Smooth"}},"LeftSurface":{"type":"Enum","value":{"enumType":"SurfaceType","value":"Smooth"}},"Locked":{"type":"bool","value":false},"Massless":{"type":"bool","value":false},"Material":{"type":"Enum","value":{"enumType":"Material","value":"Sand"}},"PivotOffset":{"type":"CFrame","value":{"position":[0,0,0],"rotation":[1,0,0,0,1,0,0,0,1]}},"Reflectance":{"type":"float","value":0},"RightSurface":{"type":"Enum","value":{"enumType":"SurfaceType","value":"Smooth"}},"RootPriority":{"type":"int","value":0},"TopSurface":{"type":"Enum","value":{"enumType":"SurfaceType","value":"SmoothNoOutlines"}},"Transparency":{"type":"float","value":0}},"referenceId":"0002e8b9-a855-e5a6-d957-00004b048e3a"},{"className":"Weld","name":"Weld","parentId":"0002e8b9-a855-e5a6-d957-00004b048e3a","path":"ServerStorage.Maps.Amazon.voxels.16786.Weld","properties":{"C0":{"type":"CFrame","value":{"position":[0,-0.5,0],"rotation":[1,0,0,0,0,-1,0,1,0]}},"C1":{"type":"CFrame","value":{"position":[-57.5,0.5,-89.5],"rotation":[1,0,0,0,0,-1,0,1,0]}},"Capabilities":{"type":"Enum","value":{"enumType":"SecurityCapabilities","value":""}},"Enabled":{"type":"bool","value":true},"Part0":{"type":"Enum","value":{"enumType":"BasePart","value":"16786"}},"Part1":{"type":"Enum","value":{"enumType":"BasePart","value":"PlayerSpawn"}}},"referenceId":"0002e8ba-90f1-e6ea-73ff-00002d37a2a1"},{"className":"Part","name":"16863","parentId":"00027302-b139-2950-51b5-00005b278fde","path":"ServerStorage.Maps.Amazon.voxels.16863","properties":{"Anchored":{"type":"bool","value":true},"AudioCanCollide":{"type":"bool","value":true},"BackSurface":{"type":"Enum","value":{"enumType":"SurfaceType","value":"Smooth"}},"BottomSurface":{"type":"Enum","value":{"enumType":"SurfaceType","value":"SmoothNoOutlines"}},"CFrame":{"type":"CFrame","value":{"position":[67,1,112],"rotation":[1,0,0,0,1,0,0,0,1]}},"CanCollide":{"type":"bool","value":true},"CanQuery":{"type":"bool","value":true},"CanTouch":{"type":"bool","value":true},"Capabilities":{"type":"Enum","value":{"enumType":"SecurityCapabilities","value":""}},"CastShadow":{"type":"bool","value":true},"CollisionGroup":{"type":"string","value":"Default"},"CollisionGroupId":{"type":"int","value":0},"CustomPhysicalProperties":{"type":"nil"},"EnableFluidForces":{"type":"bool","value":true},"FrontSurface":{"type":"Enum","value":{"enumType":"SurfaceType","value":"Smooth"}},"LeftSurface":{"type":"Enum","value":{"enumType":"SurfaceType","value":"Smooth"}},"Locked":{"type":"bool","value":false},"Massless":{"type":"bool","value":false},"Material":{"type":"Enum","value":{"enumType":"Material","value":"Sand"}},"PivotOffset":{"type":"CFrame","value":{"position":[0,0,0],"rotation":[1,0,0,0,1,0,0,0,1]}},"Reflectance":{"type":"float","value":0},"RightSurface":{"type":"Enum","value":{"enumType":"SurfaceType","value":"Smooth"}},"RootPriority":{"type":"int","value":0},"TopSurface":{"type":"Enum","value":{"enumType":"SurfaceType","value":"SmoothNoOutlines"}},"Transparency":{"type":"float","value":0}},"referenceId":"0002e8bb-2873-adde-33bb-00004deac719"}]